Workbook

Sheet Programs of HUD
A1: PDF Page | B1: Program Name | C1: Administering Office | D1: Program Summary | E1: Statutory Authority | F1: CFR Citation (Regulations) | G1: Program Website(s)
A2: 6 | B2: The Violence Against Women Act (VAWA) | C2: Offices of the Secretary & Deputy Secretary | D2: Provides housing protections for survivors of domestic violence, dating violence, sexual assault, and stalking in covered housing programs. | E2: Chapter 2 of Subtitle N of the Violence Against Women Act of 1994 (34 U.S.C. 12471, et seq.); (34 U.S.C. 12491-12496). | F2: Regulations are found at 24 CFR part 5, subpart L and in individual program regulations. The Violence Against Women Act Reauthorization Act of 2022 (Public Law 117-103, approved March 15, 2022). | G2: https://www.hud.gov/vawa
A3: 7 | B3: Self-Help Housing Property Disposition Program | C3: Offices of the Secretary & Deputy Secretary | D3: This program makes surplus Federal properties available through sale at less than fair market value to States, their subdivisions and instrumentalities, and nonprofit organizations. | E3: 40 U.S.C. 550(f)(3). | G3: https://disposal.gsa.gov/s/
A4: 8 | B4: Capacity Building for Community Development and Affordable Housing (Section 4) | C4: Community Planning and Development (CPD) | D4: Grants to national intermediaries to develop the capacity and ability of community development corporations (CDCs) and community housing development organizations (CHDOs) to carry out community development and affordable housing activities that benefit low- and moderateincome families and persons. | E4: Section 4 of the HUD Demonstration Act of 1993 (42 U.S.C. 9816 note). | G4: https://www.hud.gov/program_offices/comm_planning/section-4
A5: 9 | B5: Community Development Block Grant Disaster Recovery (CDBG-DR) Assistance | C5: Community Planning and Development (CPD) | D5: Flexible grants to help the most impacted and distressed areas recover long-term after Presidentially declared disasters. | E5: CDBG-DR assistance is largely governed by specific appropriations acts, most recently Public Law 117-328, and it is also subject to provisions of Title I of the Housing and Community Development Act of 1974 (42 U.S.C. 5301, et seq.) (made applicable by appropriations acts unless waived) and certain provisions of the Robert T. Stafford Disaster Relief and Emergency Assistance Act (42 U.S.C. 5121, et seq.). | G5: https://www.hud.gov/program_offices/comm_planning/cdbg-dr
A6: 11 | B6: Community Development Block Grants (CDBG) (Entitlement) | C6: Community Planning and Development (CPD) | D6: Funding to help metropolitan cities and urban counties meet their housing and community development needs. | E6: Title I, Housing and Community Development Act of 1974 (Public Law 93383, approved August 22, 1974) (42 U.S.C. 5301, et seq.). | F6: CDBG Program regulations are at 24 CFR part 570 and consolidated plan regulations are at 24 CFR part 91. | G6: https://www.hud.gov/program_offices/comm_planning/cdbg
A7: 13 | B7: Community Development Block Grants for Insular Areas | C7: Community Planning and Development (CPD) | D7: Funding to help certain U.S. territories meet their housing and community development needs. | E7: Title I, Housing and Community Development Act of 1974 (42 U.S.C. 5301, et seq.). | F7: CDBG Program regulations are at 24 CFR part 570 and consolidated plan regulations are at 24 CFR part 91. | G7: https://www.hud.gov/program_offices/comm_planning/cdbg
A8: 14 | B8: Community Development Block Grants (Non-Entitlement) for States and Small Cities | C8: Community Planning and Development (CPD) | D8: Funding to help States and units of local government in non-entitlement areas meet their housing and community development needs. | E8: Title I, Housing and Community Development Act of 1974 (42 U.S.C. 5301, et seq.). | F8: CDBG program regulations are at 24 CFR part 570 and consolidated plan regulations are at 24 CFR part 91. | G8: https://www.hud.gov/program_offices/comm_planning/cdbg
A9: 15 | B9: Community Development Block Grants (Section 108 Loan Guarantee) | C9: Community Planning and Development (CPD) | D9: Loan guarantee assistance for community and economic development. | E9: Section 108 of the Housing and Community Development Act of 1974 (42 U.S.C. 5308). | F9: Regulations are at 24 CFR part 570. | G9: https://www.hud.gov/program_offices/comm_planning/section108
A10: 17 | B10: Continuum of Care Program | C10: Community Planning and Development (CPD) | D10: Promotes community-wide commitment to the goal of ending homelessness; provides funding for efforts to quickly re-house homeless individuals and families while minimizing trauma and dislocation; promotes access to and effective utilization of mainstream programs; and optimizes self-sufficiency among individuals and families experiencing homelessness. | E10: Subtitle C of Title IV of the McKinney-Vento Homeless Assistance Act (42 U.S.C. 11381-11389). | F10: Regulations are at 24 CFR part 578. | G10: https://www.hud.gov/program_offices/comm_planning/coc
A11: 18 | B11: Emergency Solutions Grants (ESG) Program | C11: Community Planning and Development (CPD) | D11: Formula grants to provide emergency assistance to people who are homeless or at risk of homelessness and help them quickly regain stability in permanent housing. | E11: Subtitle B of Title IV of the McKinney-Vento Homeless Assistance Act (42 U.S.C. 11371-11378). | F11: Regulations are at 24 CFR part 576. | G11: https://www.hud.gov/program_offices/comm_planning/esg
A12: 19 | B12: Federal Surplus Property for Use to Assist Persons Experiencing Homelessness (Title V) | C12: Community Planning and Development (CPD) | D12: Enables States, local governments, and qualified nonprofit organizations to use suitable and available Federal properties which are categorized as unutilized, underutilized, excess, or surplus, to assist persons experiencing homelessness. | E12: Title V of the McKinney-Vento Homeless Assistance Act of 1987 (42 U.S.C. 11411). | F12: Regulations are at 24 CFR part 581. | G12: https://www.hud.gov/program_offices/comm_planning/titlev
A13: 20 | B13: HOME Investment Partnerships | C13: Community Planning and Development (CPD) | D13: Grants to States, units of general local government, consortia, and insular areas (“participating jurisdictions”) to implement local housing strategies to increase affordable housing opportunities for low- and very low-income families. | E13: Title II of the Cranston-Gonzalez National Affordable Housing Act (42 U.S.C. 12721, et seq.). | F13: Regulations are at 24 CFR part 92 and consolidated plan regulations are at 24 CFR part 91. | G13: https://www.hud.gov/program_offices/comm_planning/home
A14: 22 | B14: Housing Opportunities for Persons with AIDS (HOPWA) | C14: Community Planning and Development (CPD) | D14: Formula grants and competitively awarded grants to provide housing assistance and related supportive services to meet the housing needs of low-income persons living with HIV/AIDS and their families. | E14: The AIDS Housing Opportunity Act, Subtitle D of Title VIII of the CranstonGonzalez National Affordable Housing Act (42 U.S.C. 12901, et seq.). | F14: Regulations are at 24 CFR part 574. | G14: https://www.hud.gov/program_offices/comm_planning/hopwa
A15: 23 | B15: Housing Trust Fund | C15: Community Planning and Development (CPD) | D15: Provides funds to States, State-designated entities, and insular areas for the construction, rehabilitation, and preservation of rental homes and for homeownership for extremely low- and very low-income families, including homeless families. Nature of the Program: The Housing Trust Fund (HTF) provides funding to construct, rehabilitate, and preserve permanent rental and homeownership housing, primarily for extremely low-income families. At least 80 percent of the funds must be used for the production, preservation, rehabilitation, or operation of rental housing. Up to 10 percent can be used for the following homeownership activities for first-time homebuyers: production, preservation, and rehabilitation; down payment assistance, closing cost assistance, and assistance for interest rate buy-downs. Up to 10 percent may be used for reasonable administrative and planning costs. In any fiscal year with an aggregate formula allocation under $1 billion, 100 percent of the grant funds must benefit extremely low-income families or families with incomes at or below the poverty line, whichever is greater. In any fiscal year with an aggregate formula allocation over $1 billion, at least 75 percent of grant funds must benefit extremely low-income families, and the remainder must benefit very low-income families. Eligible activities and expenses include real property acquisition, site improvements and development hard costs, related soft costs, demolition, financing costs, and relocation costs. HTF-assisted rental housing units must have a minimum affordability period of 30 years. The affordability period for homeownership housing ranges from 10 to 30 years, depending on the amount of per-unit homeownership assistance. | E15: Section 1338 of the Federal Housing Enterprises Financial Safety and Soundness Act of 1992 as amended (12 U.S.C. 4568). | F15: Regulations are at 24 CFR part 93 and consolidated plan regulations are at 24 CFR part 91. | G15: https://www.hud.gov/program_offices/comm_planning/htf
A16: 24 | B16: Rural Capacity Building for Community Development and Affordable Housing Grants Program | C16: Community Planning and Development (CPD) | D16: Program Grants to national organization intermediaries for rural housing development organizations, community development corporations (CDCs), community housing development organizations (CHDOs), local governments, and Indian tribes to carry out community development and affordable housing activities that benefit low- and moderate-income families and persons in rural areas. | E16: Consolidated Appropriations Act, 2023 (Public Law 117-328, approved December 29, 2022). | G16: https://www.hudexchange.info/programs/rural-capacity-building/
A17: 25 | B17: Self-Help Homeownership Opportunity Program (SHOP) | C17: Community Planning and Development (CPD) | D17: Grants to national and regional nonprofits to fund opportunities for self-help homeownership housing. | E17: Section 11 of the Housing Opportunity Program Extension Act of 1996 (42 U.S.C. 12805 note). | G17: https://www.hud.gov/program_offices/comm_planning/shop
A18: 26 | B18: Energy Efficient Mortgage Program | C18: Office of Housing — Single Family Housing Programs | D18: Mortgage insurance to finance cost effective energy efficiency improvements. | E18: Section 513 of the Housing and Community Development Act of 1992 (Public Law 102-550, approved October 28, 1992) (12 U.S.C. 1701z-16). | F18: Regulations are at 24 CFR 203.18(i). | G18: https://www.hud.gov/program_offices/housing/sfh/eem/energy-r
A19: 27 | B19: Good Neighbor Next Door Sales Program (GNND) | C19: Office of Housing — Single Family Housing Programs | D19: Provides eligible law enforcement officers, teachers (pre-Kindergarten through 12th grade), firefighters, and emergency medical technicians with the opportunity to purchase and live in homes located in revitalization areas at a fifty percent discount off the list price of eligible properties. | E19: Section 204 of the National Housing Act (12 U.S.C. 1710). | F19: Regulations are at 24 CFR part 291, subpart F. | G19: https://www.hud.gov/program_offices/housing/sfh/reo/goodn/gnndabot
A20: 28 | B20: Home Equity Conversion Mortgage (HECM) (Section 255) | C20: Office of Housing — Single Family Housing Programs | D20: Mortgage insurance for reverse mortgages that provide borrowers who are at least 62 years old the ability to convert some of the equity in their primary residences into fixed interest rate mortgages with a single disbursement lump sum payment or adjustable interest rate mortgages with monthly streams of income or lines of credit, or a combination of both. | E20: Section 255 of the National Housing Act (12 U.S.C. 1715z-20). | F20: Regulations are at 24 CFR part 206. | G20: https://www.hud.gov/program_offices/housing/sfh/hecm/hecmabou
A21: 29 | B21: Insurance for Adjustable Rate Mortgages (ARMs) (Section 251) | C21: Office of Housing — Single Family Housing Programs | D21: Mortgage insurance for adjustable rate forward mortgages (ARMs). | E21: Section 251 of the National Housing Act (12 U.S.C. 1715z-16). | F21: Regulations are at 24 CFR 203.49. | G21: https://www.hud.gov/program_offices/housing/sfh/ins/251--df
A22: 30 | B22: Insured Mortgages on Hawaiian Home Lands (Section 247) | C22: Office of Housing — Single Family Housing Programs | D22: Insures loans to Native Hawaiians to purchase one- to four-family dwellings located on Hawaiian Home Lands, similar to Section 203(b) loans with certain exceptions. | E22: Section 247 of the National Housing Act (12 U.S.C. 1715z-12). | F22: Regulations are at 24 CFR 203.43i. | G22: https://www.hud.gov/program_offices/housing/sfh/ins/sfh_hawaiian_home_lands
A23: 31 | B23: Loss Mitigation | C23: Office of Housing — Single Family Housing Programs | D23: Measures that allow lenders to effectively work with delinquent borrowers of FHA-insured single family loans to find solutions to avoid foreclosure. | E23: Sections 204(a) and 230 of the National Housing Act (12 U.S.C. 1710(a) and 12 U.S.C. 1715u). | F23: Regulations are at 24 CFR part 203. | G23: https://www.hud.gov/program_offices/housing/sfh/nsc/lossmit
A24: 32 | B24: Manufactured Homes Loan Insurance (Title I) | C24: Office of Housing — Single Family Housing Programs | D24: Mortgage insurance for private lending institutions to finance the purchase or refinance of a new or existing manufactured home, a manufactured home lot, or a lot plus manufactured home. | E24: Section 2 of Title I of the National Housing Act (12 U.S.C. 1703). | F24: Regulations are at 24 CFR part 201. | G24: https://www.hud.gov/program_offices/housing/sfh/title/manuf14
A25: 33 | B25: Mortgage Insurance for Disaster Victims (Section 203) | C25: Office of Housing — Single Family Housing Programs | D25: Mortgage insurance for victims of a Presidentially declared major disaster who have lost their homes and are in the process of rebuilding or buying another single family home. | E25: Section 203(h) of the National Housing Act (12 U.S.C. 1709(h)). | F25: Regulations are at 24 CFR 203.18. | G25: https://www.hud.gov/program_offices/housing/sfh/ins/203h-dft
A26: 34 | B26: Mortgage Insurance for One- to Four-Family Homes (Section 203) | C26: Office of Housing — Single Family Housing Programs | D26: Mortgage insurance for purchasing or refinancing a primary residence. | E26: Sections 203(b) and 214 of the National Housing Act (12 U.S.C. 1709(b) and 12 U.S.C. 1715d). | F26: Regulations are at 24 CFR part 203. | G26: https://www.hud.gov/program_offices/housing/sfh/ins/203b--df
A27: 35 | B27: Mortgage Insurance Programs on Indian Reservations and Other Restricted Lands (Section 248) | C27: Office of Housing — Single Family Housing Programs | D27: Mortgage insurance for loans made to Native Americans to buy, build, or rehabilitate houses on Indian trust or otherwise restricted land; fundamentally the same as Section 203(b) loans. | E27: Section 248 of the National Housing Act (12 U.S.C. 1715z-13). | F27: Regulations are at 24 CFR 203.43h. | G27: https://www.hud.gov/program_offices/housing/sfh/ins/sfh248
A28: 36 | B28: Property Improvement Loan Insurance (Title I) | C28: Office of Housing — Single Family Housing Programs | D28: Mortgage insurance for loans to finance or refinance the alteration, repair or improvement of property, for the purchase and installation of fire safety equipment in existing health care facilities, and for the preservation of historic structures. | E28: Section 2 of Title I of the National Housing Act (12 U.S.C. 1703). | F28: Regulations are at 24 CFR part 201. | G28: https://www.hud.gov/program_offices/housing/sfh/title
A29: 37 | B29: Rehabilitation Loan Mortgage Insurance (Section 203(k)) | C29: Office of Housing — Single Family Housing Programs | D29: Mortgage insurance to finance the rehabilitation or purchase and rehabilitation of one- to fourunit structures. | E29: Section 203(k) of the National Housing Act (12 U.S.C. 1709(k)). | F29: Regulations are in 24 CFR 203.50. | G29: https://www.hud.gov/program_offices/housing/sfh/203k/203k--df
... A47: 56 | B47: Housing Counseling Program | C47: Office of Housing — Office of Housing Counseling | D47: Provides regulatory oversight and capacity building to HUD-approved Housing Counseling Agencies and HUD-certified counselors and awards grants to facilitate housing counseling services, addressing such needs as purchasing or renting a home, preventing foreclosure and eviction, and diminishing homelessness. | E47: Section 4(g)(3) of the Department of Housing and Urban Development Act of 1965 (42 U.S.C. 3533(g)(3)) and section 106 of the Housing and Urban Development Act of 1968 (12 U.S.C. 1701x). | F47: Regulations are at 24 CFR part 206, subpart E and part 214. | G47: https://www.hudexchange.info/programs/housingcounseling/program-description/
A48: 57 | B48: Book-Rich Environments Initiative | C48: Public and Indian Housing (PIH) — Public Housing Programs | D48: Collaboration aimed to transform public housing agencies (PHAs) into book-rich environments by providing diverse, high-quality books and other literacy tools to children and families living in HUD-assisted housing. | E48: Section 501 of the Housing and Urban Development Act of 1970 (12 U.S.C. 1701z-1). | G48: https://www.hud.gov/program_offices/public_indian_housing/bre
A49: 58 | B49: Choice Neighborhoods | C49: Public and Indian Housing (PIH) — Public Housing Programs | D49: Competitive grant program to develop severely distressed HUD housing through a comprehensive approach which transforms neighborhoods of poverty into vibrant, mixed-income neighborhoods. | E49: Choice Neighborhoods is authorized through annual appropriations acts, most recently the Consolidated Appropriations Act, 2024 (Public Law 118-42, approved March 9, 2024); section 24 of the United States Housing Act of 1937 (42 U.S.C. 1437v) . | G49: https://www.hud.gov/cn
A50: 59 | B50: ConnectHomeUSA | C50: Public and Indian Housing (PIH) — Public Housing Programs | D50: Platform for public-private collaboration to improve educational, employment, and health outcomes of HUD-assisted households by narrowing the digital divide. | E50: Section 501 of the Housing and Urban Development Act of 1970 (12 U.S.C. 1701z-1); notice published in the Federal Register on April 3, 2015, at 80 FR 18248.
A51: 60 | B51: Family Self-Sufficiency (FSS) Program | C51: Public and Indian Housing (PIH) — Public Housing Programs | D51: Promotes the development of local strategies to coordinate public and private resources that help housing choice voucher program participants, public housing tenants, and tenants in the Section 8 Project-Based Rental Assistance (PBRA) program to obtain employment that aims to enable participating families to achieve economic independence and reduce dependence on welfare assistance and rental subsidies. | E51: Section 23 of the United States Housing Act of 1937 (42 U.S.C. 1437u). | F51: Regulations are at 24 CFR part 984. | G51: https://www.hud.gov/program_offices/public_indian_housing/programs/hcv/fss
A52: 61 | B52: Housing Choice Voucher Program | C52: Public and Indian Housing (PIH) — Public Housing Programs | D52: Rental subsidies for tenants to rent units in the private market. | E52: Section 8 of the United States Housing Act of 1937 (42 U.S.C. 1437f). | F52: Regulations are at 24 CFR part 5 (certain cross-cutting requirements); 24 CFR part 982 (Section 8 Tenant-Based Housing Choice Voucher Program); 24 CFR part 984 (Section 8 and Public Housing Family Self-Sufficiency Program); and 24 CFR part 985 (Section 8 Management Assessment Program (SEMAP)). | G52: https://www.hud.gov/program_offices/public_indian_housing/programs/hcv/about/
A53: 64 | B53: Jobs Plus Initiative | C53: Public and Indian Housing (PIH) — Public Housing Programs | D53: Competitive grant program to increase earnings and advance employment outcomes for public housing residents. | E53: The Jobs Plus Initiative is authorized through annual appropriations acts, most recently the Consolidated Appropriations Act, 2024 (Public Law 118-42, approved March 9, 2024). | G53: https://www.hud.gov/program_offices/public_indian_housing/jpi
A54: 65 | B54: Moving to Work (MTW) Demonstration | C54: Public and Indian Housing (PIH) — Public Housing Programs | D54: Allows selected PHAs to test new ways of providing housing assistance intended to improve cost-effectiveness, promote self-sufficiency of assisted households, or increase housing choices for low-income families. | E54: Section 204 of the Omnibus Consolidated Rescissions and Appropriations Act of 1996 (Public Law 104-134, approved April 26, 1996). Additional MTW agencies authorized by section 599H of the Departments of Veterans Affairs and Housing and Urban Development, and Independent Agencies Appropriation Act, 1999 (Public Law 105-276, approved October 21, 1998); section 230 of the Consolidated Appropriations Act, 2008 (Public Law 110-161, approved December 26, 2007); section 232 of the Consolidated Appropriations Act, 2010 (Public Law 111-117, approved December 16, 2009); section 1101 of the Department of Defense and FullYear Continuing Appropriations Act, 2011 (Public Law 112-10, approved April 15, 2011); and section 239 of the Consolidated Appropriations Act, 2016 (Public Law 114-113, approved December 18, 2015). | G54: https://www.hud.gov/program_offices/public_indian_housing/programs/ph/mtw
A55: 66 | B55: Project-Based Voucher Program | C55: Public and Indian Housing (PIH) — Public Housing Programs | D55: Rental assistance for eligible families who live in specific housing developments or units. | E55: Section 8(o)(13) of the United States Housing Act of 1937 (42 U.S.C. 1437f(o)(13)). | F55: Regulations are at 24 CFR part 983. | G55: https://www.hud.gov/program_offices/public_indian_housing/programs/hcv/project
A56: 67 | B56: Public Housing Capital Fund | C56: Public and Indian Housing (PIH) — Public Housing Programs | D56: Funding for capital improvements to public housing units. | E56: Section 9(d) and section 30 of the United States Housing Act of 1937 (42 U.S.C. 1437g(d) and 1437z-2). | F56: Regulations are at 24 CFR part 905. | G56: https://www.hud.gov/program_offices/public_indian_housing/programs/ph/capfund
A57: 68 | B57: Public Housing Homeownership (Section 32) | C57: Public and Indian Housing (PIH) — Public Housing Programs | D57: Sale of public housing units to low-income families. | E57: Section 32 of the United States Housing Act of 1937 (42 U.S.C. 1437z-4). | F57: Regulations are at 24 CFR part 906. | G57: https://www.hud.gov/program_offices/public_indian_housing/centers/sac/homeownership/
A58: 69 | B58: Public Housing Operating Fund | C58: Public and Indian Housing (PIH) — Public Housing Programs | D58: Formula funding to public housing agencies (PHAs) for operations and management. | E58: Section 9(e), section 30, and section 35 of the United States Housing Act of 1937 (42 U.S.C. 1437g(e); 42 U.S.C. 1437z-2; 42 U.S.C. 1437z-7). | F58: Regulations are at 24 CFR part 990. | G58: https://www.hud.gov/program_offices/public_indian_housing/programs/ph/am
A59: 70 | B59: Resident Opportunity and Self-Sufficiency (ROSS) Service Coordinator Program | C59: Public and Indian Housing (PIH) — Public Housing Programs | D59: Grants for voluntary supportive services and resident empowerment activities. | E59: Section 34 of the United States Housing Act of 1937 (42 U.S.C. 1437z-6). | F59: Regulations are at 24 CFR part 964. | G59: https://www.hud.gov/program_offices/public_indian_housing/programs/ph/ross/about
A60: 71 | B60: Indian Community Development Block Grant (ICDBG) Program | C60: Public and Indian Housing (PIH) — Indian Housing Programs | D60: Grants to help American Indians and Alaska Natives (AIAN) develop viable communities. | E60: Title I of the Housing and Community Development Act of 1974 (42 U.S.C. 5301, et seq.). | F60: Regulations are at 24 CFR part 1003. | G60: https://www.hud.gov/program_offices/public_indian_housing/ih/grants/icdbg
A61: 72 | B61: Indian Housing Block Grant (IHBG) Program | C61: Public and Indian Housing (PIH) — Indian Housing Programs | D61: Grants that fund a range of affordable housing activities on Indian reservations and in Indian areas. | E61: Titles I through V of NAHASDA (25 U.S.C. 4101, et seq.). | F61: Regulations are at 24 CFR part 1000. | G61: https://www.hud.gov/program_offices/public_indian_housing/ih/grants/ihbg
A62: 73 | B62: Section 184 Indian Housing Loan Guarantee Program (Section 184) | C62: Public and Indian Housing (PIH) — Indian Housing Programs | D62: Insures home mortgages made to American Indian and Alaska Native (AIAN) families, Indian housing authorities, and Indian tribes. | E62: Section 184 of the Housing and Community Development Act of 1992 (12 U.S.C. 1715z-13a). | F62: Regulations are at 24 CFR part 1005. | G62: https://www.hud.gov/program_offices/public_indian_housing/ih/homeownership/184
A63: 74 | B63: Section 184A Native Hawaiian Housing Loan Guarantee Program (Section 184A) | C63: Public and Indian Housing (PIH) — Indian Housing Programs | D63: Insures home mortgages made to Native Hawaiian families living on Hawaiian Home Lands. | E63: Section 184A of the Housing and Community Development Act of 1992 (12 U.S.C. 1715z-13b). | F63: Regulations are at 24 CFR part 1007. | G63: https://www.hud.gov/program_offices/public_indian_housing/ih/codetalk/onap/program184a
A64: 75 | B64: Native Hawaiian Housing Block Grant (NHHBG) Program | C64: Public and Indian Housing (PIH) — Indian Housing Programs | D64: Grants that fund a range of affordable housing activities, including rental assistance both on and off Hawaiian Home Lands. | E64: Title VIII of the Native American Housing Assistance and Self-Determination Act of 1996 (NAHASDA) (25 U.S.C. 4221, et seq.). | F64: Regulations are at 24 CFR part 1006. | G64: https://www.hud.gov/program_offices/public_indian_housing/ih/codetalk/onap/nhhbgprogram
A65: 76 | B65: Tribal Housing Activities Loan Guarantee Program (Title VI) | C65: Public and Indian Housing (PIH) — Indian Housing Programs | D65: Guarantees private loans made to Indian Housing Block Grant recipients that want to finance additional grant-eligible affordable housing and related community development projects. | E65: Title VI of the Native American Housing Assistance and Self-Determination Act of 1996 (NAHASDA) (25 U.S.C. 4191, et seq.). | F65: Regulations are at 24 CFR part 1000, subpart E. | G65: https://www.hud.gov/program_offices/public_indian_housing/ih/homeownership/titlevi
A66: 77 | B66: Equal Opportunity and Nondiscrimination Requirements for HUD-Assisted Programs (Title VI, Section 504, Americans with Disabilities Act, Section 109, Age Discrimination Act, and Title IX) | C66: Fair Housing and Equal Opportunity | D66: (Title VI, Section 504, Americans with Disabilities Act, Section 109, Age Discrimination Act, and Title IX) Prohibits discrimination and requires equal opportunity to participate in and benefit from HUDassisted programs or activities. | G66: https://www.hud.gov/program_offices/fair_housing_equal_opp
A67: 80 | B67: Fair Housing Act (Title VIII) | C67: Fair Housing and Equal Opportunity | D67: Prohibits discrimination in housing and real estate-related transactions and includes an affirmative obligation to administer all federal programs relating to housing and urban development in a manner that affirmatively furthers fair housing. | E67: Title VIII of the Civil Rights Act of 1968 (42 U.S.C. 3601 et seq.). | F67: Regulations are at 24 CFR parts 5, 100, 103, and 180. | G67: https://www.hud.gov/program_offices/fair_housing_equal_opp/fair_housing_act_overview
A68: 82 | B68: Fair Housing Assistance Program (FHAP) | C68: Fair Housing and Equal Opportunity | D68: Funding to provide assistance and reimbursements to State and local fair housing enforcement agencies that enforce fair housing laws that are substantially equivalent to the Fair Housing Act. | E68: Sections 810(f) and 817 of the Civil Rights Act of 1968 (42 U.S.C. 3610; 42 U.S.C. 3616). | F68: Regulations are at 24 CFR part 115. | G68: https://www.hud.gov/program_offices/fair_housing_equal_opp/partners/FHAP
A69: 83 | B69: Fair Housing Initiatives Program (FHIP) | C69: Fair Housing and Equal Opportunity | D69: Grants to public and private entities formulating or carrying out programs to prevent or eliminate discriminatory housing practices against all protected class groups under the Federal Fair Housing Act. | E69: Section 561 of the Housing and Community Development Act of 1987 (42 U.S.C. 3616a). | F69: Regulations are at 24 CFR part 125. | G69: https://www.hud.gov/program_offices/fair_housing_equal_opp/partners/FHIP/fhip
A70: 85 | B70: Policy Development and Research Initiatives | C70: Policy Development and Research (PD&R) | D70: Supports the Department's efforts to help create cohesive, economically healthy communities by providing reliable and objective data and analysis. | E70: Title V of the Housing and Urban Development Act of 1970 (12 U.S.C. 1701z-1, et seq.). | G70: https://www.huduser.gov/portal/about/pdrabout.html
A71: 86 | B71: Community Compass Technical Assistance and Capacity Building Program | C71: Policy Development and Research (PD&R) | D71: Awards funding to technical assistance providers to help HUD’s customers implement HUD programs and policies. Nature of program: This initiative competitively awards technical assistance funding from across HUD program offices to organizations to provide technical assistance and capacity building for HUD grantees and other customers. Eligible activities for Community Compass include the following: (1) needs assessments; (2) direct technical assistance and capacity-building engagements; (3) development of products and tools; (4) self-directed and group learning (training); (5) knowledge management; (6) data reporting, analysis, and performance management; (7) Native American Housing Assistance and Self-Determination Act (NAHASDA) allocation formula administration and negotiated rulemaking support; (8) coordination; and (9) administration. | E71: Section 6(j)(3) of the United States Housing Act of 1937 (42 U.S.C. 1437d(j)(3)); sections 405 and 491 of the McKinney-Vento Homeless Assistance Act (42 U.S.C. 11361b and 11408) and Public Law 117-43 for CDBG-DR. Community Compass is further authorized and funded through annual and supplemental appropriations, most recently through the Consolidated Appropriations Act, 2024 (Public Law 118-42, approved March 9, 2024). | G71: https://www.huduser.gov/portal/ota/community-compass.html
A72: 87 | B72: Distressed Cities and Persistent Poverty Technical Assistance (DCTA) Program | C72: Policy Development and Research (PD&R) | D72: Builds the capacity of units of general local government (local governments) experiencing economic distress and assists local governments and their nonprofit partners in alleviating persistent poverty in specific areas (census tracts). | E72: Authorized by annual Appropriations Acts, most recently by the Consolidated Appropriations Act,2024 (Public Law 118-42, approved March 9, 2024). | G72: https://www.huduser.gov/portal/ota/distressed-cities-and-persistant-poverty-taprogram.html
A73: 88 | B73: Thriving Communities Technical Assistance Program | C73: Policy Development and Research (PD&R) | D73: Helps local governments ensure housing needs are considered as part of their larger infrastructure investment plans and supports equitable development in disadvantaged communities. | E73: Authorized by annual Appropriations Acts, most recently by the Consolidated Appropriations Act, 2024 (Public Law 118-42, approved March 9, 2024). | G73: https://www.huduser.gov/portal/ota/thriving-communities-ta-program.html
A74: 89 | B74: Eviction Protection Grant Program (EPGP) | C74: Policy Development and Research (PD&R) | D74: Aims to help fill the gap in access to legal assistance experienced by individuals and families facing eviction to help them reach more mutually beneficial resolutions with landlords or defend against illegal evictions. | E74: Authorized by annual Appropriations Acts, most recently by the Consolidated Appropriations Act, 2024 (Public Law 118-42, approved March 9, 2024). | G74: https://www.huduser.gov/portal/eviction-protection-grant.html
A75: 90 | B75: Davis-Bacon and Labor Standards | C75: Field Policy and Management (FPM) | D75: Oversight of administration and enforcement of Federal labor standards provisions in HUD programs. | E75: Davis-Bacon Act (40 U.S.C. 3141, et seq.); Fair Labor Standards Act of 1938 (29 U.S.C. 201, et seq.); Contract Work Hours and Safety Standards Act (40 U.S.C. 3701, et seq.); Copeland Anti-Kickback Act (18 U.S.C. 874; 40 U.S.C. 3145). | G75: https://www.hud.gov/program_offices/davis_bacon_and_labor_standards
A76: 91 | B76: Economic Opportunities for Low- and Very-Low Income Persons (Section 3) | C76: Field Policy and Management (FPM) | D76: Fosters local economic development, job opportunities, and self-sufficiency. | E76: Section 3 of the Housing and Urban Development Act of 1968 (12 U.S.C. 1701u). | F76: Regulations are at 24 CFR part 75. | G76: https://www.hud.gov/section3
A77: 92 | B77: Ginnie Mae Single-Class Mortgage-Backed Securities | C77: Government National Mortgage Association (Ginnie Mae) | D77: Guarantees timely payments on securities backed by government-insured mortgages. | E77: Section 306(g) of the National Housing Act (12 U.S.C. 1721(g)). | F77: Regulations are at 24 CFR part 320. | G77: https://www.ginniemae.gov/about_us/what_we_do/Pages/programs_products.aspx
A78: 93 | B78: Ginnie Mae Multiclass Securities | C78: Government National Mortgage Association (Ginnie Mae) | D78: Guarantees the timely payment of principal and interest on multiclass securities backed by government-insured mortgages as provided by the terms of the multiclass security. | E78: Section 306(g) of the National Housing Act (12 U.S.C. 1721(g)). | F78: Regulations are at 24 CFR part 330. | G78: https://www.ginniemae.gov/investors/multiclass_resources/Pages/multiclass-securitiesguide.aspx
A79: 95 | B79: Lead Hazard Control and Healthy Homes Program | C79: Lead Hazard Control and Healthy Homes Program | D79: address housing-related health and safety hazards; demonstration projects and research, outreach and education related to lead hazard control and healthy homes issues; enforcement of the Lead Safe Housing Rule and the Lead Disclosure Rule. | E79:  Lead-Based Paint Poisoning Prevention Act (42 U.S.C. 4821, et seq.);  Residential Lead-Based Paint Hazard Reduction Act of 1992 (Title X of the Housing and Community Development Act of 1992; 42 U.S.C. 4851, et seq.);  Sections 501 and 502 of the Housing and Urban Development Act of 1970 (12 U.S.C. 1701z-1 and 1701z-2). | F79: Regulations are at 24 CFR part 35. | G79: https://www.hud.gov/program_offices/healthy_homes
A80: 97 | B80: Low Income Housing Tax Credit Pilot (Tax Credit Pilot) | C80: Temporary Programs — HERA (Public Law 110-289) | D80: HERA established a pilot program to streamline the review process for FHA mortgage insurance applications for projects with equity from the Low-Income Housing Tax Credit (LIHTC) program. In 2012, FHA launched the pilot program to refinance mortgage debt under FHA’s Section 223(f) program on transactions that would receive LIHTC equity. On February 21, 2019, FHA announced the expansion of the pilot program (Mortgagee Letter 2019-03 and Notice: H 2019-03) to include new construction and substantial rehabilitation projects under its Section 221(d)(4) and Section 220 programs. The expanded pilot program continues FHA’s effort to ensure faster and more efficient processing for low-risk, LIHTC transactions by eliminating redundant reviews. FHA multifamily transactions with LIHTCs account for approximately 30 percent of FHA’s total multifamily volume. By aligning FHA’s Section 221(d)(4) and Section 220 programs with the LIHTC program, the Department anticipated and has realized more production and preservation of critically needed affordable multifamily housing. LIHTCs are codified at 26 U.S.C. 42. | G80: https://www.hud.gov/program_offices/housing/mfh/map/maphome/taxcredit
A81: 97 | B81: Rental Assistance Demonstration (RAD) | C81: Temporary Programs — Consolidated and Further Continuing Appropriations Act, 2012 | D81: The Consolidated and Further Continuing Appropriations Act, 2012 authorized the creation of a demonstration designed to preserve and improve public housing and certain other multifamily housing through the voluntary conversion of properties assisted under section 9 of the United States Housing Act of 1937 (public housing), the Moderate Rehabilitation Program (Mod Rehab), the Rent Supplement Program (Rent Supp), and the Rental Assistance Program (RAP), to assistance under a project-based subsidy contract under section 8 of the 1937 Act. Subsequent legislation authorized the voluntary conversion of the Section 202 and 811 Project Rental Assistance Contract (202 PRAC and 811 PRAC) programs. The program has a competitive component and a non-competitive component, but no new funding is appropriated for these conversions. The competitive component allows conversion of a maximum number of units from the Section 9 account (for public housing conversions) or from the Project-Based Rental Assistance (PBRA) account (amounts appropriated for mod rehab) for Mod Rehab conversion to long-term Section 8 rental assistance contracts or project-based voucher contracts. The conversions are administered by public housing agencies and other qualified entities. The non-competitive component allows Mod Rehab and 202 PRAC property owners to convert assistance to long-term Section 8 rental assistance contracts or project-based voucher contracts. | G81: http://www.hud.gov/rad
A82: 98 | B82: Tribal HUD-VASH | C82: Temporary Programs — Consolidated and Further Continuing Appropriations Act, 2015 | D82: The Tribal HUD-Veterans Affairs Supportive Housing program (Tribal HUD-VASH) provides rental assistance and supportive services to Native American veterans who are homeless or at risk of homelessness living on or near a reservation or other Indian areas. HUD provides grants to eligible Tribes and Tribally Designated Housing Entities (TDHEs), which partner with the U.S. Department of Veterans Affairs to provide case management and services to eligible Native American veterans. Housing assistance is either tenant-based or project-based and is made available by grants to Tribes and TDHEs that are eligible to receive Indian Housing Block Grant funding under the Native American Housing Assistance and Self-Determination Act of 1996. This program is funded through annual appropriations acts, most recently through the Consolidated Appropriations Act, 2024 (Public Law 118-42, approved March 9, 2024). | G82: https://www.hud.gov/program_offices/public_indian_housing/ih/tribalhudvash
A83: 98 | B83: Youth Homelessness Demonstration Program | C83: Temporary Programs — Consolidated Appropriations Act, 2016 | D83: The Youth Homelessness Demonstration Program (YHDP) aims to both demonstrate how a comprehensive approach to serving youth, age 24 and under, who are experiencing homelessness can reduce the number of youths experiencing homelessness and to try new strategies for serving youth experiencing homelessness. This is done by providing grants to States, counties, cities, townships, and nonprofits on a competitive basis through a notice of funding opportunity (NOFO) in which HUD selects communities for participation. Recipients are to serve youth experiencing homelessness, age 24 and under, including unaccompanied and pregnant or parenting youth, by developing and implementing a community plan to prevent and end youth homelessness. This program is funded through annual appropriations acts, most recently through the Consolidated Appropriations Act, 2024 (Public Law 118-42, approved March 9, 2024). | G83: https://www.hud.gov/program_offices/comm_planning/yhdp
A84: 99 | B84: Mobility Demonstration (Community Choice Demonstration) | C84: Temporary Programs — Consolidated Appropriations Act, 2019 | D84: The Community Choice Demonstration (CCD), formerly known as the HCV Mobility Demonstration, builds upon recent research that shows growing up in neighborhoods with lower levels of poverty improves children’s academic achievement and long-term chances of success and reduces intergenerational poverty. The CCD supports selected PHAs in addressing barriers to accessing housing choices by offering housing mobility-related services to increase the number of voucher families with children living in opportunity areas. Through October 2028, these PHA sites will provide housing mobility-related services to approximately 9,400 families. In addition to offering housing mobility-related services, participating PHAs work together in their regions to adopt administrative policies that further enable housing mobility, increase landlord participation, and reduce barriers for families to move across PHA jurisdictions through portability. The CCD includes a rigorous, independent evaluation to determine what services are most effective at helping families move to opportunity areas. HUD also intends to make materials developed for the Demonstration available to all PHAs for use in their own communities. The Consolidated Appropriations Act, 2019 (Public Law 116-6, approved February 15, 2019) (providing initial funding), and the Further Consolidated Appropriations Act, 2020 (Public Law 116-94, approved December 20, 2019) (expanding CCD). | G84: https://www.hud.gov/program_offices/public_indian_housing/programs/hcv/communitychoicede
A85: 99 | B85: Recovery Housing Program (RHP) | C85: Temporary Programs — Further Consolidated Appropriations Act, 2020 | D85: The Recovery Housing Program (RHP) is a pilot program, authorized by Section 8071 of the SUPPORT for Patients and Communities Act (“SUPPORT Act”), that provides stable, temporary housing to individuals in recovery from a substance use disorder. The assistance is limited, per individual, to a period of not more than two years or until the individual secures permanent housing, whichever is earlier. The SUPPORT Act requires amounts appropriated or amounts otherwise made available to RHP grantees (states and the District of Columbia) be treated as CDBG funds under title I of the Housing and Community Development Act of 1974 (42 U.S.C. 5301, et seq.) (the “HCD Act”), unless otherwise provided in Section 8071 or modified by waivers and alternative requirements published in the Federal Register. HUD published two Federal Register notices describing the program rules, waivers, and alternative requirements applicable for RHP grantees and activities: 1) FY2020 Notice published on November 25, 2020 and 2) FY2021 Notice published on July 21, 2021. HUD distributes amounts appropriated for RHP in accordance with the SUPPORT Act and the Federal Register notice published on April 17, 2019, entitled “SUPPORT for Patients and Communities Act; Establishment of Funding Formula” (84 FR 16027). This program is funded through annual appropriations acts, most recently through the Consolidated Appropriations Act, 2024 (Public Law 118-42, approved March 9, 2024). | G85: https://www.hud.gov/program_offices/comm_planning/rhp
A86: 100 | B86: American Rescue Plan Act of 2021 | C86: Temporary Programs — American Rescue Plan Act of 2021 | D86: The American Rescue Plan Act of 2021 (the “ARP Act”) includes supplemental appropriations to numerous HUD programs to address the continued impact of COVID-19. The ARP Act provided the following funds for HUD and HUD programs: 
A87: 101 | B87: Green and Resilient Retrofit Program (GRRP) | C87: Temporary Programs — Inflation Reduction Act (IRA) | D87: GRRP provides owners of HUD-assisted multifamily housing with capital resources to reduce carbon emissions, make utility efficiency improvements, incorporate renewable energy sources, and make properties more resilient against the effects of climate hazards. HUD has three paths (cohorts) of funding available to meet the needs of properties at all stages of redevelopment. The first funding path, Elements awards, provides funding for owners to include proven and meaningful climate resilience and utility efficiency measures in projects that are already in the process of a recapitalization transaction. The second path, Leading Edge awards, provides funding for ambitious retrofit activities to achieve an advanced green certification. This is geared toward properties in the planning stages of a recapitalization effort. The final funding path, Comprehensive awards, provides funding to properties with the highest need for climate resilience and utility efficiency upgrades, regardless of prior development or environmental retrofit experience. | G87: https://www.hud.gov/GRRP
A88: 101 | B88: Preservation And Reinvestment Initiative for Community Enhancement (PRICE) | C88: Temporary Programs — Consolidated Appropriations Act, 2023 | D88: The Consolidated Appropriations Act, 2023, created competitive grants to “preserve and revitalize manufactured housing and eligible manufactured housing communities.” The Appropriations Act limited grant recipients to States, units of general local government, residentowned manufactured housing communities, cooperatives, nonprofit entities including consortia of nonprofit entities, community development financial institutions, Indian tribes, or other entities approved by the Secretary. This program was most recently funded through the Consolidated Appropriations Act, 2024 (Public Law 118-42, approved March 9, 2024). | G88: https://www.hud.gov/program_offices/comm_planning/price
A89: 101 | B89: Pathways to Removing Obstacles to Housing (PRO Housing) | C89: Temporary Programs — Consolidated Appropriations Act, 2023 | D89: The Consolidated Appropriations Act, 2023, created competitive grants to State and local governments, metropolitan planning organizations, and multijurisdictional entities for the identification and removal of barriers to affordable housing production and preservation through activities intended to further develop, evaluate, and implement housing policy plans, improve housing strategies, and facilitate affordable housing production and preservation. The Consolidated Appropriations Act, 2024 (Public Law 118-42, approved March 9, 2024) provided further funding. | G89: https://www.hud.gov/program_offices/comm_planning/pro_housing
A90: 102 | B90: NeighborWorks America | C90: Related Agencies | D90: Provides financial support, technical assistance, and training for community-based revitalization efforts. | E90: Title VI of the Housing and Community Development Amendments of 1978 Act (42 U.S.C. 8101, et seq.). | G90: http://www.neighborworks.org
A91: 103 | B91: U.S. Interagency Council on Homelessness | C91: Related Agencies | D91: Promotes and coordinates the Federal response to homelessness and national partnerships that work to reduce and end homelessness. | E91: Title II of the McKinney-Vento Homeless Assistance Act (42 U.S.C. 11311, et seq.). | G91: https://www.usich.gov/
A92: 104 | B92: EnVision Center Demonstration | C92: Inactive Programs — Office of the Secretary | D92: A pilot program for public-private collaboration to improve educational and employment opportunities, health outcomes, and community participation of HUD-assisted households. HUD has not accepted new applications under this program since January 2021.
A93: 104 | B93: Community Development Block Grant CARES Act (CDBG-CV) | C93: Inactive Programs — Community Planning and Development | D93: Grants to states, insular areas, and local governments to prevent, prepare for, and respond to the spread of COVID-19.
A94: 104 | B94: Economic Development Initiative (“Competitive EDI”) Grants | C94: Inactive Programs — Community Planning and Development | D94: Grants to directly enhance the security of Section 108 guaranteed loans or to improve the viability of the same Section 108 assisted project.
A95: 104 | B95: Resident Opportunity and Self-Sufficiency (ROSS) for Education Program | C95: Inactive Programs — Community Planning and Development | D95: The ROSS for Education Program, also known as Project SOAR (Students + Opportunities + Achievements = Results) was a demonstration program reflecting HUD’s commitment to expand educational services to youth living in HUD-assisted housing. Project SOAR provided grant funding to public housing authorities to deploy education navigators to provide individualized assistance to public housing youth between the ages of 15 and 20 and their families in Free Application for Federal Student Aid (FAFSA) completion, financial literacy and college readiness, postsecondary program applications and post-acceptance assistance. HUD awarded approximately $2 million to nine PHAs in 2016 to hire education navigators.
A96: 104 | B96: Rural Housing Stability Assistance Program | C96: Inactive Programs — Community Planning and Development | D96: Re-housing and other help for individuals moving from emergency or transitional shelters to permanent housing or improves the housing situations of individuals and families who are homeless or in the worst housing situations in the geographic area, stabilizes the housing of individuals and families who are in imminent danger of losing housing, and improves the ability of the lowest-income residents of the community to afford stable housing. While funds are appropriated, HUD exercises its discretion to allocate the funds to the Continuum of Care program.
A97: 104 | B97: Veterans Housing Rehabilitation and Modification Pilot Program (VHRMP) | C97: Inactive Programs — Community Planning and Development | D97: Section 1079 of the National Defense Authorization Act for Fiscal Year 2015 authorized grants to qualified nonprofit organizations to rehabilitate and modify the primary residence of eligible veterans. Conducted in consultation with the Secretary of Veterans Affairs, grant funds were used to modify or rehabilitate the home of low-income disabled veterans. The program was funded in 2016 and subsequent appropriations acts, most recently the Consolidated Appropriations Act, 2023.
A98: 105 | B98: Juvenile Reentry Assistance Program | C98: Inactive Programs — Public and Indian Housing | D98: The Juvenile Reentry Assistance Program sought to alleviate collateral consequences associated with a juvenile or criminal record by assisting youth, up to age 24, residing in public or Section 8-assisted housing; or youth who would be residing in public or Section 8-assisted housing but for their criminal record. As a one-time transfer, the Department of Justice’s Office of Juvenile Justice and Delinquency Prevention transferred through interagency agreement approximately $2.05 million to HUD for the specific purpose of helping youth to improve chances for reentry, reduce recidivism, and address the challenges youth face while trying to reintegrate into their communities. The program expired in 2019.
A99: 105 | B99: FHA-Home Affordable Modification Program (FHA-HAMP) | C99: Inactive Programs — Housing/FHA — Single Family Housing Programs | D99: FHA-HAMP was an enhanced loss mitigation option that combined a loan modification with a partial claim, allowing homeowners to reduce monthly mortgage payment options and avoid foreclosure. Please note that FHA also uses this term to describe one of its current loss mitigation waterfall options.
A100: 105 | B100: Mortgage Insurance for Manufactured Home Parks (Section 207) | C100: Inactive Programs — Housing/FHA — Single Family Housing Programs | D100: Provided mortgage insurance to help finance the construction or rehabilitation of manufactured home parks. HUD has not endorsed a loan under this program since 2013.
A101: 105 | B101: Congregate Housing Services Program (CHSP) | C101: Inactive Programs — Housing/FHA — Multifamily Housing Programs | D101: Federal grants to eligible housing projects for the elderly and persons with disabilities. HUD has neither solicited nor funded applications for new grants under CHSP since 1995, but Congress has provided funds to extend expiring grants on an annual basis.
A102: 105 | B102: Senior Preservation Rental Assistance Contracts (SPRAC) | C102: Inactive Programs — Housing/FHA — Multifamily Housing Programs | D102: The purpose of the SPRAC Program is to prevent the displacement of currently unassisted income-eligible elderly residents residing in eligible Section 202 Direct Loan properties that may result from the owner’s refinancing or recapitalization of the property.
A103: 105 | B103: Supportive Services Demonstration (IWISH) | C103: Inactive Programs — Housing/FHA — Multifamily Housing Programs | D103: The Supportive Services Demonstration for Elderly Households in HUD-Assisted Multifamily Housing tests the Integrated Wellness in Supportive Housing (IWISH) model, funded onsite staff (Resident Wellness Director and a Wellness nurse) at HUD-assisted housing developments that either predominantly or exclusively served households aged 62 and over. A NOFO was last published for Fiscal Year 2015. The following names table and index are intended to assist readers in finding programs that are often referred to using the shorthand of their statutory designation, both in this document and in statutes. Commonly Used Program Names Table Title I Program Name Community Development Block Grants I Property Improvement Loans and Manufactured Home Loans Non-Discrimination on the Basis of Disability by Public Entities in HousingRelated Programs, Services, and Activities Equal Opportunity in HUD-Assisted Programs II VI VI Title VI Loan Guarantee Program VIII X Fair Housing Act Lead Hazard Control Section 203(b) 203(k) Program Name Economic Opportunities for Low- and Very Low-Income Persons Low-Income Rental Assistance Section 108 Loan Guarantees Nondiscrimination in Programs and Activities Receiving Assistance Under Title I of the Housing and Community Development Act of 1974 Indian Home Loan Guarantees Supportive Housing for the Elderly One- to Four-Family Home Mortgage Insurance Rehabilitation Mortgage Insurance Multifamily Rental Housing Cooperative Housing Statute Housing and Community Development Act of 1974 National Housing Act Americans with Disabilities Act Civil Rights Act of 1964 Section 504 of the Rehabilitation Act Civil Rights Act of 1968 Native American Housing Assistance and Self-Determination Act of 1996 Civil Rights Act of 1968 Housing and Community Development Act of 1992 Statute Housing and Urban Development Act of 1968 United States Housing Act of 1937 Housing and Community Development Act of 1974 Housing and Community Development Act of 1974 Housing and Community Development Act of 1992 Housing Act of 1959 National Housing Act National Housing Act National Housing Act National Housing Act Section Program Name 221(d)(2) Homeownership Assistance for Low- and Moderate-Income Families 221(d)(3) Multifamily Rental Housing for ModerateIncome Families 223(f) Existing Multifamily Rental Housing Mortgage Insurance for Housing for the Elderly Nursing Homes, Intermediate Care Facilities, and Board and Care Homes Condominium Housing Hospitals Home Equity Conversion Mortgage (HECM) Non-Discrimination on the Basis of Disability in HUD-Assisted Programs Supportive Housing for Persons with Disabilities Statute National Housing Act National Housing Act National Housing Act National Housing Act National Housing Act National Housing Act National Housing Act National Housing Act Rehabilitation Act of 1973 Housing Act of 1959 Program Index American Rescue Plan Act ..................... 100 Appropriations, 2012 RAD...................................................... 97 Appropriations, 2014 IWISH ................................................ 107 Appropriations, 2015 Tribal HUD-VASH .............................. 98 Appropriations, 2016 Resident Opportunity and SelfSufficiency (ROSS) for Education Program .......................................... 105 Youth Homelessness Demo.................. 98 Appropriations, 2019 Mobility Demonstration (Community Mobility Choice Demonstration ...... 99 Appropriations, 2023 .............................. 101 PRICE ................................................. 101 PRO Housing ...................................... 101 Book-Rich Environments Initiative .......... 57 Capacity Building for Community Development and Affordable Housing ... 8 Choice Neighborhoods.............................. 58 CHSP....................................................... 106 Community Compass Technical Assistance and Capacity Building Program ............ 86 Community Development Block Grants (CDBG) Disaster Recovery Assistance ................ 9 Entitlement ........................................... 11 For Insular Areas .................................. 13 Indian .................................................... 71 Non-Entitlement for States and Small Cities ................................................ 14 Section 108 Loan Guarantee ................ 15 Competitive EDI Grants ......................... 105 ConnectHomeUSA ................................... 59 Continuum of Care Program ..................... 17 Davis-Bacon and Labor Standards............ 90 Defense Authorization, 2015 Veteran Home Repair Demo .............. 106 Emergency Solutions Grants (ESG) ......... 18 Energy Efficient Mortgage Program ......... 26 Equal Opportunity ..................................... 77 Fair Housing Act ....................................... 80 Fair Housing Assistance (FHAP).............. 82 Fair Housing Initiatives (FHIP) ................ 83 Family Self-Sufficiency ............................ 60 FHA-Home Affordable Modification Program ............................................... 106 Ginnie Mae Mortgage-Backed Securities I .............. 92 Multiclass Securities............................. 93 Good Neighbor Next Door........................ 27 HECM ....................................................... 28 HERA........................................................ 97 Tax Credit Pilot .................................... 97 HOME Investment Partnerships ............... 20 Housing Choice Voucher Program ........... 61 Housing Counseling Program ................... 56 Housing Opportunities for Persons With AIDS ..................................................... 22 Housing Trust Fund .................................. 23 Indian Housing Block Grants.................... 72 Inflation Reduction Act........................... 101 Green and Resilient Retrofit Program (GRRP) .......................................... 101 Interagency Council on Homelessness ... 104 Jobs Plus.................................................... 64 Juvenile Reentry Assistance Program ..... 106 Lead Hazard Control and Healthy Homes 95 Loss Mitigation ......................................... 31 MAHRA.................................................... 50 Manufactured Home Construction and Safety Standards.................................... 40 Mark-to-Market Program .......................... 41 Moving to Work........................................ 65 Multifamily Housing Service Coordinators ............................................................... 47 Native Hawaiian Housing Block Grants ... 75 Neighborhood Reinvestment Corporation ............................................................. 102 Policy Development and Research ........... 85 Project-Based Vouchers ............................ 66 Public Housing Capital Fund .................... 67 Public Housing Operating Fund................ 69 ROSS......................................................... 70 Rural Capacity Building ........................... 24 Rural Housing Stability Assistance ........ 105 Section 184................................................ 73 Section 184A............................................. 74 Section 202................................................ 51 Section 203................................................ 34 Section 203(h) ........................................... 33 Section 203(k) ........................................... 37 Section 204(g) ........................................... 38 Section 207.............................................. 106 Section 207/223(f) .................................... 43 Section 213................................................ 42 Section 220................................................ 45 Section 221(d)(3) and (4) .......................... 49 Section 231................................................ 44 Section 232................................................ 55 Section 232/223(f) .................................... 55 Section 241................................................ 46 Section 242................................................ 54 Section 247................................................ 30 Section 248................................................ 35 Section 251................................................ 29 Section 3.................................................... 91 Section 32.................................................. 68 Section 542(b) and (c) ............................... 48 Section 811................................................ 52 SHOP ........................................................ 25 Title I Manufactured Homes Loan Insurance . 32 Property Improvement Loan Insurance 36 Title V ....................................................... 19 Title VI ...................................................... 76

Sheet About
A1: Programs of HUD — 2025 Reference Spreadsheet
A3: Source: U.S. Department of Housing and Urban Development, "Programs of HUD 2025" (Major Mortgage, Grant, Assistance, and Regulatory Programs, 2025).
A4: Original PDF filename: HUDPrograms2025.pdf (109 pages, dated December 17, 2024).
A6: Coverage: All programs listed in the HUD 2025 reference document, including:
A7: • Active programs in each program office (rows grouped by Administering Office)
A8: • Temporary programs authorized through specific appropriations acts
A9: • Related agencies (NeighborWorks America, U.S. Interagency Council on Homelessness)
A10: • Inactive programs (programs receiving no new funds or only renewal funding)
A12: Total programs: 102
A14: Column notes:
A15: • Program Summary: drawn from the brief introductory description in each program's PDF entry (the italicized teaser sentence(s) appearing immediately under the program title in the source document). Trimmed to two sentences where the original was longer.
A16: • Statutory Authority: extracted from each program's "Legal Authority" section. For Temporary Programs, the authorizing appropriations act (with Public Law number) is used.
... A98: Columns G–H (added Oct. 2, 2026): 'Why it's in this group' explains the placement (usually the authorizing law; sometimes that law routes the money through another program's statute, e.g., EHV and RAD to Section 8 or CDBG-DR and RHP to HCDA Title I, or leaves the definition to HUD), and 'Authorizing law' cites the statute or appropriations act.

Sheet FPI (HUD)
A1: AL Number | B1: Program Title | C1: Popular Name | D1: Agency | E1: Sub-Agency | F1: Objective | G1: Assistance Types | H1: Beneficiary Types | I1: Applicant Types | J1: FY2025 Obligation — FPI Headline ($, SAM estimate) | K1: FY2024 Obligation ($, USAspending actual) | L1: FY2023 Obligation ($, USAspending actual) | M1: Obligations (raw JSON, all years)
A2: 14.021 | B2: Green and Resilient Retrofit Program | C2: GRRP | D2: Department of Housing and Urban Development | E2: Assistant Secretary for Housing -- Federal Housing Commissioner | F2: The Green and Resilient Retrofit Program offers loans and grants for HUD-assisted multifamily properties to improve energy or water efficiency, enhance indoor air quality or sustainability, implement the use of zero-emission electricity generation, low-emission building materials or processes, energy storage, or building electrification strategies, or address climate resilience. | G2: Direct Loans | H2: Private nonprofit institution/organization,Profit organization,Public nonprofit institution/organization | I2: Private nonprofit institution/organization (includes institutions of higher education and hospitals),Profit organization,Public nonprofit institution/organization (includes institutions of higher education and hospitals) | J2: 0 | K2: 590926365 | L2: 9025948 | M2: [{"x":"2023","sam_estimate":0.0,"sam_actual":75000000.0,"usa_spending_actual":9025948.0},{"x":"2024","sam_estimate":0.0,"sam_actual":87000000.0,"usa_spending_actual":590926365.0},{"x":"2025","sam_estimate":0.0,"sam_actual":0.0,"usa_spending_actual":19471823.2}]
A3: 14.022 | B3: Housing Counseling Program Homeownership Initiative | D3: Department of Housing and Urban Development | E3: Assistant Secretary for Housing -- Federal Housing Commissioner | F3: The Homeownership Initiative (HI) helps to bridge the homeownership gap by increasing homeownership rates among historically underserved borrowers. HUD-approved Intermediaries, Multi-State Organizations, and State Housing Finance Agencies will receive fixed amount awards to provide culturally sensitive linguistically appropriate pre-purchase and post-purchase counseling that results in home purchase. | G3: Project Grants | I3: Local (includes State-designated lndian Tribes, excludes institutions of higher education and hospitals,Other private institutions/organizations,Other public institution/organization,Private nonprofit institution/organization (includes institutions of higher education and hospitals),Public nonprofit institution/organization (includes institutions of higher education and hospitals),State,State (includes District of Columbia, public institutions of higher education and hospitals) | J3: 0 | K3: 10000000 | L3: 0 | M3: [{"x":"2023","sam_estimate":0.0,"sam_actual":67000000.0,"usa_spending_actual":0.0},{"x":"2024","sam_estimate":0.0,"sam_actual":61000000.0,"usa_spending_actual":10000000.0},{"x":"2025","sam_estimate":0.0,"sam_actual":0.0,"usa_spending_actual":-66186.5}]
A4: 14.023 | B4: Community Development Block Grant- PRO Housing Competition | C4: PRO Housing | D4: Department of Housing and Urban Development | E4: Assistant Secretary for Community Planning and Development | F4: PRO (Pathways to Removing Obstacles) to Housing provides competitive grant funds for the identification and removal of barriers to affordable housing production and preservation. | G4: Project Grants | I4: Government - General,Local (includes State-designated lndian Tribes, excludes institutions of higher education and hospitals,Native American Organizations (includes lndian groups, cooperatives, corporations, partnerships, associations),Non-Government - General,Other private institutions/organizations,Other public institution/organization,State | J4: 0 | K4: 84935900 | L4: 0 | M4: [{"x":"2023","sam_estimate":0.0,"sam_actual":10000000.0,"usa_spending_actual":0.0},{"x":"2024","sam_estimate":0.0,"sam_actual":84935898.0,"usa_spending_actual":84935899.92},{"x":"2025","sam_estimate":0.0,"sam_actual":100064101.0,"usa_spending_actual":0.0}]
A5: 14.024 | B5: Community Development Block Grant- PRICE Competition | C5: CDBG-PRICE | D5: Department of Housing and Urban Development | E5: Assistant Secretary for Community Planning and Development | F5: The Community Development Block Grant - Preservation and Reinvestment Initiative for Community Enhancement (CDBG-PRICE) competition provides competitive grant funds to help preserve and revitalize manufactured housing and eligible manufactured housing communities and assist in the redevelopment of manufactured housing communities as replacement housing that is affordable. | G5: Project Grants | I5: Federally Recognized lndian Tribal Governments,Government - General,Local (includes State-designated lndian Tribes, excludes institutions of higher education and hospitals,Minority group,Native American Organizations (includes lndian groups, cooperatives, corporations, partnerships, associations),Non-Government - General,Profit organization,Quasi-public nonprofit institution/organization,State | J5: 0 | K5: 0 | L5: 0 | M5: [{"x":"2023","sam_estimate":0.0,"sam_actual":225000000.0,"usa_spending_actual":0.0},{"x":"2024","sam_estimate":0.0,"sam_actual":0.0,"usa_spending_actual":0.0},{"x":"2025","sam_estimate":0.0,"sam_actual":0.0,"usa_spending_actual":0.0}]
A6: 14.108 | B6: Rehabilitation Mortgage Insurance | C6: FHA Rehabilitation Mortgage- 203(k) | D6: Department of Housing and Urban Development | E6: Assistant Secretary for Housing -- Federal Housing Commissioner | F6: FHA's 203(k) Rehabilitation Mortgage program is HUD's primary program for the rehabilitation and repair of one to four family properties. It is an important tool for community and neighborhood revitalization and for expanding homeownership opportunities. The 203(k) program works with either a purchase or refinance transaction and allows the cost of making repairs and/or improvement to be included in the loan amount. | G6: Guaranteed / Insured Loans | H6: Anyone/general public,Individual/Family | I6: Individual/Family | J6: 0 | K6: 0 | L6: 0 | M6: [{"x":"2023","sam_estimate":0.0,"sam_actual":0.0,"usa_spending_actual":0.0},{"x":"2024","sam_estimate":0.0,"sam_actual":0.0,"usa_spending_actual":0.0},{"x":"2025","sam_estimate":0.0,"sam_actual":0.0,"usa_spending_actual":0.0}]
A7: 14.110 | B7: Manufactured Home Loan Insurance (Title I) | C7: Manufactured Home Loan Insurance (Title I) | D7: Department of Housing and Urban Development | E7: Assistant Secretary for Housing -- Federal Housing Commissioner | F7: To help people purchase a manufactured home or refinance an existing manufactured home loan. mortgage. | G7: Sale, Exchange, or Donation of Property or Goods | H7: Anyone/general public,Individual/Family | I7: Individual/Family | J7: 0 | K7: 0 | L7: 0 | M7: [{"x":"2023","sam_estimate":0.0,"sam_actual":0.0,"usa_spending_actual":0.0},{"x":"2024","sam_estimate":0.0,"sam_actual":4000000.0,"usa_spending_actual":0.0},{"x":"2025","sam_estimate":0.0,"sam_actual":0.0,"usa_spending_actual":0.0}]
A8: 14.117 | B8: Mortgage Insurance Homes | C8: FHA Home Mortgage Insurance- 203(b) | D8: Department of Housing and Urban Development | E8: Assistant Secretary for Housing -- Federal Housing Commissioner | F8: Helps enable people to purchase a home or refinance an existing mortgage. | G8: Guaranteed / Insured Loans | H8: Anyone/general public,Individual/Family | I8: Individual/Family | J8: 0 | K8: 0 | L8: 0 | M8: [{"x":"2023","sam_estimate":0.0,"sam_actual":195799000.0,"usa_spending_actual":0.0},{"x":"2024","sam_estimate":0.0,"sam_actual":225000000.0,"usa_spending_actual":0.0},{"x":"2025","sam_estimate":0.0,"sam_actual":0.0,"usa_spending_actual":0.0}]
A9: 14.119 | B9: Mortgage Insurance Homes for Disaster Victims | C9: Mortgage Insurance for DIsaster Victims- 203(h) | D9: Department of Housing and Urban Development | E9: Assistant Secretary for Housing -- Federal Housing Commissioner | F9: To help victims of a Presidentially-declared disaster whose home was destroyed undertake homeownership on a sound basis. | G9: Sale, Exchange, or Donation of Property or Goods | H9: Anyone/general public,Individual/Family | I9: Individual/Family | J9: 0 | K9: 0 | L9: 0 | M9: [{"x":"2023","sam_estimate":0.0,"sam_actual":0.0,"usa_spending_actual":0.0},{"x":"2024","sam_estimate":0.0,"sam_actual":0.0,"usa_spending_actual":0.0},{"x":"2025","sam_estimate":0.0,"sam_actual":0.0,"usa_spending_actual":0.0}]
A10: 14.122 | B10: Mortgage Insurance Homes in Urban Renewal Areas | C10: (220 Homes) | D10: Department of Housing and Urban Development | E10: Assistant Secretary for Housing -- Federal Housing Commissioner | F10: To help eligible entities to purchase and/or rehabilitate homes in urban renewal areas. | G10: Guaranteed / Insured Loans | H10: Anyone/general public,Individual/Family | I10: Anyone/general public,Individual/Family,Local (includes State-designated lndian Tribes, excludes institutions of higher education and hospitals,Non-Government - General,Other private institutions/organizations,Other public institution/organization,Private nonprofit institution/organization (includes institutions of higher education and hospitals),Profit organization,Public nonprofit institution/organization (includes institutions of higher education and hospitals),Sponsored organization,State | J10: 0 | K10: 0 | L10: 0 | M10: [{"x":"2023","sam_estimate":0.0,"sam_actual":0.0,"usa_spending_actual":0.0},{"x":"2024","sam_estimate":0.0,"sam_actual":0.0,"usa_spending_actual":0.0},{"x":"2025","sam_estimate":0.0,"sam_actual":0.0,"usa_spending_actual":0.0}]
A11: 14.126 | B11: Mortgage Insurance Cooperative Projects | C11: Cooperative Housing Mortgage Insurance - Section 213 | D11: Department of Housing and Urban Development | E11: Assistant Secretary for Housing -- Federal Housing Commissioner | F11: Enables nonprofit cooperative ownership housing corporations or trusts to develop or sponsor the development of housing projects to be operated as cooperatives. Section 213 allows investors to provide good quality multifamily housing to be sold to such nonprofit corporations or trusts upon completion of construction or rehabilitation. | G11: Guaranteed / Insured Loans | H11: Private nonprofit institution/organization,Profit organization,Public nonprofit institution/organization,Sponsored organization | I11: Private nonprofit institution/organization (includes institutions of higher education and hospitals),Public nonprofit institution/organization (includes institutions of higher education and hospitals),Quasi-public nonprofit institution/organization | J11: 0 | K11: 0 | L11: 0 | M11: [{"x":"2023","sam_estimate":0.0,"sam_actual":0.0,"usa_spending_actual":0.0},{"x":"2024","sam_estimate":0.0,"sam_actual":0.0,"usa_spending_actual":0.0},{"x":"2025","sam_estimate":0.0,"sam_actual":0.0,"usa_spending_actual":0.0}]
A12: 14.128 | B12: Mortgage Insurance Hospitals | C12: (Section 242 - Mortgage Insurance for Hospitals) | D12: Department of Housing and Urban Development | E12: Assistant Secretary for Housing -- Federal Housing Commissioner | F12: To facilitate the affordable financing of hospitals for the care and treatment of persons who are acutely ill or who otherwise require medical care and related services of the kind customarily furnished only or most effectively by hospitals. | G12: Guaranteed / Insured Loans | H12: Disabled (e.g. Deaf, Blind, Physically Disabled),Individual/Family,Physically Afflicted (e.g. TB, Arthritis, Heart Disease) | I12: Private nonprofit institution/organization (includes institutions of higher education and hospitals),Profit organization | J12: 0 | K12: 0 | L12: 0 | M12: [{"x":"2023","sam_estimate":0.0,"sam_actual":482000000.0,"usa_spending_actual":0.0},{"x":"2024","sam_estimate":0.0,"sam_actual":960000000.0,"usa_spending_actual":0.0},{"x":"2025","sam_estimate":0.0,"sam_actual":0.0,"usa_spending_actual":0.0}]
A13: 14.129 | B13: Mortgage Insurance Nursing Homes, Intermediate Care Facilities, Board and Care Homes and Assisted Living Facilities | C13: Section (232) | D13: Department of Housing and Urban Development | E13: Assistant Secretary for Housing -- Federal Housing Commissioner | F13: To provide mortgage insurance to HUD-approved lenders to facilitate the construction or rehabilitation of nursing homes, intermediate care facilities, board and care homes and assisted living facilities, to allow purchase or refinancing with or without repairs of projects not requiring substantial rehabilitation, and to provide loan insurance to install fire safety equipment. | G13: Guaranteed / Insured Loans | H13: Disabled (e.g. Deaf, Blind, Physically Disabled),Physically Afflicted (e.g. TB, Arthritis, Heart Disease) | I13: Other private institutions/organizations,Private nonprofit institution/organization (includes institutions of higher education and hospitals),Profit organization,Specialized group (e.g. health professionals, students, veterans) | J13: 0 | K13: 0 | L13: 0 | M13: [{"x":"2023","sam_estimate":0.0,"sam_actual":3142000000.0,"usa_spending_actual":0.0},{"x":"2024","sam_estimate":0.0,"sam_actual":3142000000.0,"usa_spending_actual":0.0},{"x":"2025","sam_estimate":0.0,"sam_actual":0.0,"usa_spending_actual":0.0}]
A14: 14.133 | B14: Mortgage Insurance Purchase of Units in Condominiums | C14: Mortgage Insurance- Condominium Units | D14: Department of Housing and Urban Development | E14: Assistant Secretary for Housing -- Federal Housing Commissioner | F14: To enable individuals and families to purchase or refinance eligible units in condominium projects. | G14: Guaranteed / Insured Loans | H14: Anyone/general public,Individual/Family | I14: Individual/Family | J14: 0 | K14: 0 | L14: 0 | M14: [{"x":"2023","sam_estimate":0.0,"sam_actual":0.0,"usa_spending_actual":0.0},{"x":"2024","sam_estimate":0.0,"sam_actual":0.0,"usa_spending_actual":0.0},{"x":"2025","sam_estimate":0.0,"sam_actual":0.0,"usa_spending_actual":0.0}]
A15: 14.134 | B15: Mortgage Insurance Rental Housing | C15: Mortgage Insurance for Rental Housing -Section 207 | D15: Department of Housing and Urban Development | E15: Assistant Secretary for Housing -- Federal Housing Commissioner | F15: HUD insures mortgage loans to finance the construction or rehabilitation of a broad range of multifamily rental housing through a variety of programs linked in the Related Federal Assistance section. Though Section 207 itself is no longer active, this assistance listing is used to provide total FHA multifamily mortgage commitments across those programs. Due to challenges in breaking out projected commitments by each listing, the activity is summed and reported here. | G15: Guaranteed / Insured Loans | H15: Anyone/general public,Individual/Family | I15: Other private institutions/organizations,Private nonprofit institution/organization (includes institutions of higher education and hospitals),Profit organization | J15: 0 | K15: 0 | L15: 0 | M15: [{"x":"2023","sam_estimate":0.0,"sam_actual":19214000000.0,"usa_spending_actual":0.0},{"x":"2024","sam_estimate":0.0,"sam_actual":17513000000.0,"usa_spending_actual":0.0},{"x":"2025","sam_estimate":0.0,"sam_actual":0.0,"usa_spending_actual":0.0}]
A16: 14.135 | B16: Mortgage Insurance Rental and Cooperative Housing for Moderate Income Families and Elderly, Market Interest Rate | C16: New Construction or Substantial Rehabilitation of Rental Housing -221(d)(4) | D16: Department of Housing and Urban Development | E16: Assistant Secretary for Housing -- Federal Housing Commissioner | F16: Section 221(d)(4) insures mortgage loans to facilitate the new construction or substantial rehabilitation of multifamily rental or cooperative housing for moderate-income families, elderly, and the handicapped. Single Room Occupancy (SRO) projects may also be insured under this section. (See program 14.184). | G16: Guaranteed / Insured Loans | H16: Anyone/general public,Individual/Family,Private nonprofit institution/organization,Profit organization,Public nonprofit institution/organization | I16: Individual/Family,Private nonprofit institution/organization (includes institutions of higher education and hospitals),Profit organization,Public nonprofit institution/organization (includes institutions of higher education and hospitals) | J16: 0 | K16: 0 | L16: 0 | M16: [{"x":"2023","sam_estimate":0.0,"sam_actual":0.0,"usa_spending_actual":0.0},{"x":"2024","sam_estimate":0.0,"sam_actual":0.0,"usa_spending_actual":0.0},{"x":"2025","sam_estimate":0.0,"sam_actual":0.0,"usa_spending_actual":0.0}]
A17: 14.138 | B17: Mortgage Insurance Rental Housing for the Elderly | C17: New Construction and Substantial Rehabilitation for Rental Housing for the Elderly - Section 231 | D17: Department of Housing and Urban Development | E17: Assistant Secretary for Housing -- Federal Housing Commissioner | F17: To provide quality rental housing for the elderly. | G17: Guaranteed / Insured Loans | H17: Anyone/general public,Disabled (e.g. Deaf, Blind, Physically Disabled),Physically Afflicted (e.g. TB, Arthritis, Heart Disease),Private nonprofit institution/organization,Profit organization,Public nonprofit institution/organization,Senior Citizen (60+) | I17: Private nonprofit institution/organization (includes institutions of higher education and hospitals),Profit organization,Public nonprofit institution/organization (includes institutions of higher education and hospitals),Specialized group (e.g. health professionals, students, veterans) | J17: 0 | K17: 0 | L17: 0 | M17: [{"x":"2023","sam_estimate":0.0,"sam_actual":0.0,"usa_spending_actual":0.0},{"x":"2024","sam_estimate":0.0,"sam_actual":0.0,"usa_spending_actual":0.0},{"x":"2025","sam_estimate":0.0,"sam_actual":0.0,"usa_spending_actual":0.0}]
... A40: 14.248 | B40: Community Development Block Grants Section 108 Loan Guarantees | C40: (Section 108) | D40: Department of Housing and Urban Development | E40: Assistant Secretary for Community Planning and Development | F40: To provide communities with a source of financing for economic development, housing rehabilitation, public facilities, and large scale physical development projects. | G40: Guaranteed / Insured Loans | H40: Individual/Family,Low Income,Moderate Income | I40: Government - General,Other public institution/organization,State,U.S. Territories and possessions | J40: 0 | K40: 0 | L40: 0 | M40: [{"x":"2023","sam_estimate":0.0,"sam_actual":300000000.0,"usa_spending_actual":0.0},{"x":"2024","sam_estimate":0.0,"sam_actual":400000000.0,"usa_spending_actual":0.0},{"x":"2025","sam_estimate":0.0,"sam_actual":0.0,"usa_spending_actual":0.0}]
A41: 14.249 | B41: Section 8 Moderate Rehabilitation Single Room Occupancy | D41: Department of Housing and Urban Development | E41: Assistant Secretary for Community Planning and Development | F41: The Section 8 Moderate Rehabilitation Single Room Occupancy Program provides rental assistance to homeless individuals. Under the program, HUD entered into Annual Contributions Contracts (ACCs) with public housing agencies (PHAs) in connection with the moderate rehabilitation of residential properties that, when rehabilitation is completed, will contain multiple single room dwelling units. Funding for new projects ceased after 2011. Expiring contracts are now renewed. | G41: Project Grants | H41: Individual/Family | I41: Private nonprofit institution/organization (includes institutions of higher education and hospitals) | J41: 0 | K41: 67118327 | L41: 64836067 | M41: [{"x":"2023","sam_estimate":0.0,"sam_actual":0.0,"usa_spending_actual":64836067.0},{"x":"2024","sam_estimate":0.0,"sam_actual":0.0,"usa_spending_actual":67118327.0},{"x":"2025","sam_estimate":0.0,"sam_actual":0.0,"usa_spending_actual":5885553.0}]
A42: 14.251 | B42: Economic Development Initiative, Community Project Funding, and Miscellaneous grants | C42: Congressional Grants | D42: Department of Housing and Urban Development | E42: Office of Community Planning and Development | F42: The annual appropriation of funds to the Department and the accompanying Conference Report or Congressional Record accompanying the appropriation set forth grants in a specified amount to designated organizations for the activities specified by Congress. | G42: Project Grants | H42: Federal,Federally Recognized Indian Tribal Governments,Local,Native American Organizations,Other private institution/organization,Other public institution/organization,Preschool,Private nonprofit institution/organization,Public nonprofit institution/organization,Quasi-public nonprofit organization,School,State,U.S. Territories | I42: Local (includes State-designated lndian Tribes, excludes institutions of higher education and hospitals,Native American Organizations (includes lndian groups, cooperatives, corporations, partnerships, associations),Public nonprofit institution/organization (includes institutions of higher education and hospitals),State (includes District of Columbia, public institutions of higher education and hospitals) | J42: 0 | K42: 11423477 | L42: 2815228723 | M42: [{"x":"2023","sam_estimate":0.0,"sam_actual":4498694848.0,"usa_spending_actual":2815228723.0},{"x":"2024","sam_estimate":0.0,"sam_actual":0.0,"usa_spending_actual":11423477.0},{"x":"2025","sam_estimate":0.0,"sam_actual":0.0,"usa_spending_actual":0.0}]
A43: 14.252 | B43: Section 4 Capacity Building for Community Development and Affordable Housing | C43: Section 4 Capacity Building | D43: Department of Housing and Urban Development | E43: Assistant Secretary for Community Planning and Development | F43: The Section 4 program builds the capacity of Community Development Corporations (CDCs) and Community Housing Development Organizations (CHDOs) to serve their communities and low- and moderate-income families with community development and affordable housing activities. | G43: Project Grants | H43: Private nonprofit institution/organization | I43: Other private institutions/organizations | J43: 0 | K43: 83000000 | L43: 41000000 | M43: [{"x":"2023","sam_estimate":0.0,"sam_actual":41000000.0,"usa_spending_actual":41000000.0},{"x":"2024","sam_estimate":0.0,"sam_actual":83000000.0,"usa_spending_actual":83000000.0},{"x":"2025","sam_estimate":0.0,"sam_actual":0.0,"usa_spending_actual":0.0}]
A44: 14.256 | B44: Neighborhood Stabilization Program (Recovery Act Funded) | D44: Department of Housing and Urban Development | E44: Office of Community Planning and Development | F44: Neighborhood stabilization through acquisition and rehabilitation, land banking, disposition, or demolition of abandoned and foreclosed residential property. Also, to develop viable urban communities, by providing decent housing and a suitable living environment, and by expanding economic opportunities, principally for persons of low and moderate income. | G44: Project Grants | H44: Low Income | I44: Government - General,Local (includes State-designated lndian Tribes, excludes institutions of higher education and hospitals,Private nonprofit institution/organization (includes institutions of higher education and hospitals),Public nonprofit institution/organization (includes institutions of higher education and hospitals),State (includes District of Columbia, public institutions of higher education and hospitals) | J44: 0 | K44: 0 | L44: 0 | M44: [{"x":"2023","sam_estimate":0.0,"sam_actual":0.0,"usa_spending_actual":0.0},{"x":"2024","sam_estimate":0.0,"sam_actual":0.0,"usa_spending_actual":0.0},{"x":"2025","sam_estimate":0.0,"sam_actual":0.0,"usa_spending_actual":0.0}]
A45: 14.259 | B45: Community Compass Technical Assistance and Capacity Building | C45: Community Compass TA | D45: Department of Housing and Urban Development | E45: Assistant Secretary for Policy Development and Research | F45: Community Compass brings together technical assistance funding appropriations from across HUD program offices, including the offices of Community Planning and Development, Fair Housing and Equal Opportunity, Housing, Public and Indian Housing, and Policy Development and Research. This cross-funding approach recognizes that HUD’s grantees, subgrantees, and other customers often interact with a variety of HUD programs as they deliver housing or community development services. Community Compass allows for holistic technical assistance to address the program and policy implementation deficiencies and skill gaps of grantees and subgrantees across multiple HUD programs, often within the same engagement. | G45: Project Grants | H45: Federally Recognized Indian Tribal Governments,Local,Public nonprofit institution/organization,Sponsored organization,State,U.S. Territories | I45: Federally Recognized lndian Tribal Governments,Native American Organizations (includes lndian groups, cooperatives, corporations, partnerships, associations),Other private institutions/organizations,Private nonprofit institution/organization (includes institutions of higher education and hospitals),Profit organization,Public nonprofit institution/organization (includes institutions of higher education and hospitals),Small business (less than 500 employees),State,State (includes District of Columbia, public institutions of higher education and hospitals) | J45: 0 | K45: -1060000 | L45: 1.5277355e+08 | M45: [{"x":"2023","sam_estimate":0.0,"sam_actual":184833190.0,"usa_spending_actual":152773550.14},{"x":"2024","sam_estimate":0.0,"sam_actual":69303801.0,"usa_spending_actual":-1060000.0},{"x":"2025","sam_estimate":0.0,"sam_actual":69936955.0,"usa_spending_actual":0.0}]
A46: 14.261 | B46: National Homeless Data Analysis Project (NHDAP) | C46: National Homeless Data Analysis Project (NHDAP) | D46: Department of Housing and Urban Development | E46: Assistant Secretary for Community Planning and Development | F46: National Homeless Data Analysis Project (NHDAP) provides critical resources to HUD and the homelessness response systems to improve homelessness response data collection, analysis, and reporting; integrate data collection efforts in Homeless Management Information Systems (HMIS) with other federal funding streams; enhance the ability for HUD and communities to report and analyze data about persons experiencing homelessness; produce standards and specifications for data entry and reporting for all HMIS-generated reports, analyze point-in-time and longitudinal analysis system data to produce the Annual Homeless Assessment Report (AHAR); and provide technical assistance on HMIS implementation. | G46: Project Grants | H46: Local,Private nonprofit institution/organization,Public nonprofit institution/organization,State | I46: Non-Government - General,Other public institution/organization,State | J46: 0 | K46: -588329.39 | L46: -175157.19 | M46: [{"x":"2023","sam_estimate":0.0,"sam_actual":4550000.0,"usa_spending_actual":-175157.19},{"x":"2024","sam_estimate":0.0,"sam_actual":9350000.0,"usa_spending_actual":-588329.39},{"x":"2025","sam_estimate":0.0,"sam_actual":0.0,"usa_spending_actual":0.0}]
A47: 14.265 | B47: Rural Capacity Building for Community Development and Affordable Housing Grants | C47: Rural Capacity Building Program | D47: Department of Housing and Urban Development | E47: Assistant Secretary for Community Planning and Development | F47: The Rural Capacity Building program enhances the capacity and ability of rural housing development organizations, Community Development Corporations (CDCs), Community Housing Development Organizations (CHDOs), local governments, and Indian tribes (eligible beneficiaries) to carry out affordable housing and community development activities in rural areas for the benefit of low- and moderate-income families and persons. The Rural Capacity Building program achieves this by funding National Organizations with expertise in rural housing and rural community development who work directly to build the capacity of eligible beneficiaries. | G47: Project Grants | H47: Federally Recognized Indian Tribal Governments,Local,Private nonprofit institution/organization | I47: Other private institutions/organizations | J47: 0 | K47: 0 | L47: 9231410.4 | M47: [{"x":"2023","sam_estimate":0.0,"sam_actual":10000000.0,"usa_spending_actual":9231410.43},{"x":"2024","sam_estimate":0.0,"sam_actual":6000000.0,"usa_spending_actual":0.0},{"x":"2025","sam_estimate":0.0,"sam_actual":0.0,"usa_spending_actual":0.0}]
A48: 14.267 | B48: Continuum of Care Program | C48: See Notice of Funding Opportunity [NOFO] for additional information. | D48: Department of Housing and Urban Development | E48: Assistant Secretary for Community Planning and Development | F48: The program is designed to promote community-wide commitment to the goal of ending homelessness; provide funding for efforts by nonprofit providers, States, and local governments to quickly house homeless individuals and families while minimizing the trauma and dislocation caused to homeless individuals, families, and communities by homelessness; promote access to and effective utilization of mainstream programs by homeless individuals and families; and optimize self-sufficiency among individuals and families experiencing homelessness. Continuum of Care Program funds may be used to pay for the eligible costs used to establish and operate projects under five program components: (i) permanent housing, which includes permanent supportive housing for persons with disabilities, and rapid rehousing; (ii) transitional housing; (iii) supportive services only; (iv) Homeless Management Information Systems (HMIS), and (v) in some cases, homelessness prevention. | G48: Project Grants | H48: Individual/Family | I48: Government - General,Local (includes State-designated lndian Tribes, excludes institutions of higher education and hospitals,Other private institutions/organizations,Quasi-public nonprofit institution/organization,Specialized group (e.g. health professionals, students, veterans),State | J48: 0 | K48: 2965446336 | L48: 2.5883551e+09 | M48: [{"x":"2023","sam_estimate":0.0,"sam_actual":3261008611.0,"usa_spending_actual":2588355061.93},{"x":"2024","sam_estimate":0.0,"sam_actual":3192650000.0,"usa_spending_actual":2965446336.0},{"x":"2025","sam_estimate":0.0,"sam_actual":0.0,"usa_spending_actual":69568361.82}]
A49: 14.269 | B49: Hurricane Sandy Community Development Block Grant Disaster Recovery Grants (CDBG-DR) | C49: Community Development Block Grant Disaster Recovery program for Hurricane Sandy and other qualifying disasters occurring in 2011, 2012 and 2013 | D49: Department of Housing and Urban Development | E49: Assistant Secretary for Community Planning and Development | F49: The overall CDBG program objective is to develop viable urban communities, by providing decent housing and a suitable living environment, and by expanding economic opportunities, principally for persons of low and moderate income. CDBG DR program funds appropriated by P.L. 113-2 are for necessary expenses related to disaster relief, long-term recovery, restoration of infrastructure and housing, and economic revitalization in the most impacted and distressed areas resulting from a major disaster declaration due to Hurricane Sandy and other eligible events in calendar years 2011, 2012, and 2013. | G49: Formula Grants | H49: Homeowner,Individual/Family,Low Income,Moderate Income,Private nonprofit institution/organization,Public nonprofit institution/organization,Small business | I49: Local (includes State-designated lndian Tribes, excludes institutions of higher education and hospitals,State,U.S. Territories and possessions | J49: 0 | K49: -140842.94 | L49: -1 | M49: [{"x":"2023","sam_estimate":0.0,"sam_actual":0.0,"usa_spending_actual":-1.0},{"x":"2024","sam_estimate":0.0,"sam_actual":0.0,"usa_spending_actual":-140842.94},{"x":"2025","sam_estimate":0.0,"sam_actual":0.0,"usa_spending_actual":0.0}]
A50: 14.272 | B50: National Disaster Resilience Competition | C50: Community Development Block Grant P. L. 113-2 | D50: Department of Housing and Urban Development | E50: Assistant Secretary for Community Planning and Development | F50: The overall CDBG program objective is to develop viable urban communities, by providing decent housing and a suitable living environment, and by expanding economic opportunities, principally for persons of low and moderate income. The National Resilient Disaster Competition program funds appropriated by P.L. 113-2 are available for resilient recovery projects and necessary expenses related to disaster relief, long-term recovery, restoration of infrastructure and housing, and economic revitalization in the most impacted and distressed areas resulting from a major disaster declared pursuant to the due to Hurricane Sandy and other eligible events in calendar years 2011, 2012, and 2013. | G50: Project Grants | H50: Anyone/general public,Homeowner,Interstate,Local,Low Income,Moderate Income,Private nonprofit institution/organization,Profit organization,Public nonprofit institution/organization,Senior Citizen (60+),Small business,State | I50: Local (includes State-designated lndian Tribes, excludes institutions of higher education and hospitals,State,U.S. Territories and possessions | J50: 0 | K50: 0 | L50: -606138.41 | M50: [{"x":"2023","sam_estimate":0.0,"sam_actual":0.0,"usa_spending_actual":-606138.41},{"x":"2024","sam_estimate":0.0,"sam_actual":0.0,"usa_spending_actual":0.0},{"x":"2025","sam_estimate":0.0,"sam_actual":0.0,"usa_spending_actual":0.0}]
A51: 14.275 | B51: Housing Trust Fund | C51: Housing Trust Fund | D51: Department of Housing and Urban Development | E51: Assistant Secretary for Community Planning and Development | F51: To expand and preserve the supply of affordable housing, particularly rental housing, for extremely low-income and very low income households. | G51: Formula Grants | H51: State | I51: State | J51: 0 | K51: 2.0558172e+08 | L51: 6.8655661e+08 | M51: [{"x":"2023","sam_estimate":0.0,"sam_actual":688096848.0,"usa_spending_actual":686556608.11},{"x":"2024","sam_estimate":0.0,"sam_actual":216961850.0,"usa_spending_actual":205581716.74},{"x":"2025","sam_estimate":0.0,"sam_actual":278000000.0,"usa_spending_actual":40280086.6}]
A52: 14.276 | B52: Youth Homelessness Demonstration Program | C52: Youth Homelessness Demonstration Program | D52: Department of Housing and Urban Development | E52: Assistant Secretary for Community Planning and Development | F52: The goal of the Youth Homeless Demonstration Program (YHDP) is to support selected communities in the development and implementation of a coordinated community approach to preventing and ending youth homelessness and sharing that experience with and mobilizing communities around the country toward the same end. The population to be served by this demonstration program is youth experiencing homelessness, age 24 and under, including unaccompanied youth and pregnant or parenting youth who are experiencing homelessness. HUD will award approximately $72,000,000 in YHDP under this NOFO through funding appropriated for fiscal year (FY) 2023 through the Consolidated Appropriations Act, 2023 (Public Law 117-328) ("FY 2023 Appropriations Act). The FY 2023 Appropriations Act appropriated this funding to HUD "to implement projects to demonstrate how a comprehensive approach to serving homeless youth, age 24 and under ... can dramatically reduce youth homelessness.” | G52: Project Grants | H52: Individual/Family,Youth (16-21) | I52: Individual/Family | J52: 0 | K52: 1.1129417e+08 | L52: 67424988 | M52: [{"x":"2023","sam_estimate":0.0,"sam_actual":92041882.0,"usa_spending_actual":67424987.95},{"x":"2024","sam_estimate":0.0,"sam_actual":123881123.0,"usa_spending_actual":111294174.62},{"x":"2025","sam_estimate":0.0,"sam_actual":72000000.0,"usa_spending_actual":3991525.0}]
A53: 14.277 | B53: Youth Homeless System Improvement Grants | C53: YHSIG | D53: Department of Housing and Urban Development | E53: Assistant Secretary for Community Planning and Development | F53: The objectives of the Youth Homeless System Improvement Grants (YHSIG), HUD will award approximately $25,000,000 to support communities, including but not limited to the communities assisted under the matter preceding this proviso in establishing and implementing a response system for youth homelessness or for improving their existing system. | G53: Project Grants | I53: Federally Recognized lndian Tribal Governments,Public nonprofit institution/organization (includes institutions of higher education and hospitals),State | J53: 0 | K53: 0 | L53: 0 | M53: [{"x":"2023","sam_estimate":0.0,"sam_actual":25000000.0,"usa_spending_actual":0.0},{"x":"2024","sam_estimate":0.0,"sam_actual":0.0,"usa_spending_actual":0.0},{"x":"2025","sam_estimate":0.0,"sam_actual":0.0,"usa_spending_actual":0.0}]
A54: 14.278 | B54: Veterans Housing Rehabilitation and Modification Program | C54: Veterans Housing Rehabilitation and Modification Program | D54: Department of Housing and Urban Development | E54: Assistant Secretary for Community Planning and Development | F54: The purpose of the Veterans Housing Rehabilitation and Modification Program is to award grants to nonprofit veterans service organizations to rehabilitate and modify the primary residence of disabled and low-income veterans. Funds may be used to support eligible activities that serve the following objectives: 1) Modify and rehabilitate the primary residence of disabled and low-income veterans; 2) Rehabilitate such residence that is in a state of interior or exterior disrepair; and 3) Install energy efficient features or equipment. | G54: Project Grants | H54: Private nonprofit institution/organization | I54: Private nonprofit institution/organization (includes institutions of higher education and hospitals) | J54: 0 | K54: 1000000 | L54: 0 | M54: [{"x":"2023","sam_estimate":0.0,"sam_actual":0.0,"usa_spending_actual":0.0},{"x":"2024","sam_estimate":0.0,"sam_actual":9000000.0,"usa_spending_actual":1000000.0},{"x":"2025","sam_estimate":0.0,"sam_actual":0.0,"usa_spending_actual":0.0}]
A55: 14.311 | B55: Single Family Property Disposition | C55: HUD Homes | D55: Department of Housing and Urban Development | E55: Assistant Secretary for Housing -- Federal Housing Commissioner | F55: To sell HUD single family Real Estate Owned (REO) properties in a manner that expands homeownership opportunities, strengthens neighborhoods and communities, and ensures a maximum return to the FHA mortgage insurance fund. | G55: Sale, Exchange, or Donation of Property or Goods | H55: Federal,Public nonprofit institution/organization,State | I55: Anyone/general public,Federal,Individual/Family,Local (includes State-designated lndian Tribes, excludes institutions of higher education and hospitals,State (includes District of Columbia, public institutions of higher education and hospitals) | J55: 0 | K55: 0 | L55: 0 | M55: [{"x":"2023","sam_estimate":0.0,"sam_actual":0.0,"usa_spending_actual":0.0},{"x":"2024","sam_estimate":0.0,"sam_actual":0.0,"usa_spending_actual":0.0},{"x":"2025","sam_estimate":0.0,"sam_actual":0.0,"usa_spending_actual":0.0}]
A56: 14.313 | B56: Dollar Home Sales | C56: Dollar Home Program, $1 Home Program | D56: Department of Housing and Urban Development | E56: Assistant Secretary for Housing -- Federal Housing Commissioner | F56: To expand HUD's partnership with local governments in helping to foster housing opportunities for low-to-moderate income families and address specific community needs. | G56: Sale, Exchange, or Donation of Property or Goods | H56: Local | I56: Local (includes State-designated lndian Tribes, excludes institutions of higher education and hospitals | J56: 0 | K56: 0 | L56: 0 | M56: [{"x":"2023","sam_estimate":0.0,"sam_actual":0.0,"usa_spending_actual":0.0},{"x":"2024","sam_estimate":0.0,"sam_actual":0.0,"usa_spending_actual":0.0},{"x":"2025","sam_estimate":0.0,"sam_actual":0.0,"usa_spending_actual":0.0}]
A57: 14.316 | B57: Housing Counseling Training Program | C57: Housing Counseling Training Grant | D57: Department of Housing and Urban Development | E57: Assistant Secretary for Housing -- Federal Housing Commissioner | F57: This program supports, under cooperative agreements with HUD, the delivery of a broad array of training activities for counselors from agencies participating in HUD's Housing Counseling program. The primary objectives of the program are to improve and standardize the quality of counseling provided by housing counselors working with HUD-approved housing counseling agencies and to make training accessible and affordable. | G57: Project Grants | H57: Specialized group (e.g. health professionals, students, veterans) | I57: Private nonprofit institution/organization (includes institutions of higher education and hospitals),Public nonprofit institution/organization (includes institutions of higher education and hospitals) | J57: 0 | K57: 2750000 | L57: -92315.5 | M57: [{"x":"2023","sam_estimate":0.0,"sam_actual":9000000.0,"usa_spending_actual":-92315.5},{"x":"2024","sam_estimate":0.0,"sam_actual":5000000.0,"usa_spending_actual":2750000.0},{"x":"2025","sam_estimate":0.0,"sam_actual":0.0,"usa_spending_actual":1880217.72}]
A58: 14.322 | B58: Tenant Education and Outreach Program | C58: (TEO) | D58: Department of Housing and Urban Development | E58: Assistant Secretary for Housing -- Federal Housing Commissioner | F58: The purpose of the Tenant Education and Outreach (TEO) Program is to support tenant capacity building at eligible existing Project-Based Section 8 properties with the goal of preserving decent, safe, and sanitary housing within the Section 8 program. | G58: Project Grants | H58: Individual/Family,Low Income,Specialized group (e.g. health professionals, students, veterans) | I58: Private nonprofit institution/organization (includes institutions of higher education and hospitals),Profit organization,Small business (less than 500 employees) | J58: 0 | K58: 10000000 | L58: 0 | M58: [{"x":"2023","sam_estimate":0.0,"sam_actual":16000000.0,"usa_spending_actual":0.0},{"x":"2024","sam_estimate":0.0,"sam_actual":0.0,"usa_spending_actual":10000000.0},{"x":"2025","sam_estimate":0.0,"sam_actual":0.0,"usa_spending_actual":0.0}]
A59: 14.326 | B59: Project Rental Assistance Demonstration (PRA Demo) Program of Section 811 Supportive Housing for Persons with Disabilities | C59: Section 811 PRA | D59: Department of Housing and Urban Development | E59: Assistant Secretary for Housing -- Federal Housing Commissioner | F59: The Project Rental Assistance (PRA) provides funding to state housing agencies for project-based rental operating assistance for extremely low-income persons with disabilties. The primary purpose is to identify, stimulate, and support innovate state-level strategies that will transform and increase housing for low-income persons with disabilities while also making available appropriate support and services. | G59: Project Grants | H59: Disabled (e.g. Deaf, Blind, Physically Disabled),Individual/Family,Low Income | I59: Local (includes State-designated lndian Tribes, excludes institutions of higher education and hospitals,State (includes District of Columbia, public institutions of higher education and hospitals) | J59: 0 | K59: 22911883 | L59: 3547685.3 | M59: [{"x":"2023","sam_estimate":0.0,"sam_actual":105999999.0,"usa_spending_actual":3547685.34},{"x":"2024","sam_estimate":0.0,"sam_actual":148000000.0,"usa_spending_actual":22911882.74},{"x":"2025","sam_estimate":0.0,"sam_actual":0.0,"usa_spending_actual":2050839.25}]
A60: 14.327 | B60: Performance Based Contract Administrator Program | C60: PBCA Program | D60: Department of Housing and Urban Development | E60: Assistant Secretary for Housing -- Federal Housing Commissioner | F60: It is the policy of the United States to promote the general welfare of the Nation by employing funds and credit of the Nation, as established in section 2 of the 1937 Act, of assisting States and their political subdivisions {e.g., Public Housing Authorities (PHA)s} to remedy the unsafe housing conditions and the acute shortage of decent and safe dwellings for low-income families as well as address the shortage of housing affordable to low-income families. The PBCA program furthers these policies by effectuating authority explicitly under section 8(b)(1) of the 1937 Act for HUD to enter into Annual Contributions Contracts (ACCs) with PHAs for the administration of Section 8 Housing Assistance Payments (HAP) contracts. For the purpose of aiding lower-income families in obtaining a decent place to live and of promoting economically mixed housing, assistance payments may be made with respect to existing housing in accordance with the provisions of this section. For the project-based subprograms authorized under Section 8, the 1937 Act authorizes HUD to enter into an ACC with a PHA, as defined in section 3(b)(6)(A) of the 1937 Act. The ACC is the contractual mechanism to support the PHA’s public purpose in making the assistance payments to Section 8 project owners. This program provides assistance to PHAs for the administration of Project-Based Section 8 program within a State. | G60: Direct Payments for a Specified Use | H60: Low Income | I60: Other public institution/organization,State | J60: 0 | K60: 0 | L60: 0 | M60: [{"x":"2023","sam_estimate":0.0,"sam_actual":418000000.0,"usa_spending_actual":0.0},{"x":"2024","sam_estimate":0.0,"sam_actual":448000000.0,"usa_spending_actual":0.0},{"x":"2025","sam_estimate":0.0,"sam_actual":0.0,"usa_spending_actual":0.0}]
A61: 14.401 | B61: Fair Housing Assistance Program | C61: (FHAP) | D61: Department of Housing and Urban Development | E61: Assistant Secretary for Fair Housing and Equal Opportunity | F61: Provide assistance to State and local fair housing enforcement agencies for complaint processing, training, technical assistance, education and outreach, data and information systems and other activities that will further fair housing within the agency's jurisdiction. The intent of the Fair Housing Assistance Program (FHAP) is to build a coordinated intergovernmental enforcement of fair housing laws and provide incentives for States and localities to assume a greater share of responsibility for administering fair housing laws. | G61: Formula Grants | H61: Anyone/general public,Individual/Family | I61: Other public institution/organization,State | J61: 0 | K61: 22691322 | L61: 27732585 | M61: [{"x":"2023","sam_estimate":0.0,"sam_actual":27778249.0,"usa_spending_actual":27732584.92},{"x":"2024","sam_estimate":0.0,"sam_actual":24984994.0,"usa_spending_actual":22691321.64},{"x":"2025","sam_estimate":0.0,"sam_actual":26400000.0,"usa_spending_actual":1702505.78}]
A62: 14.408 | B62: Fair Housing Initiatives Program | C62: (FHIP) Department of Housing and Urban Development, Office of Fair Housing and Equal Opportunity | D62: Department of Housing and Urban Development | E62: Assistant Secretary for Fair Housing and Equal Opportunity | F62: To develop, implement, carry out, or coordinate programs and/or activities to educate the public about, as well as provide enforcement of, fair housing rights under the Fair Housing Act; 42 U.S.C. 3601-3619 or State or local laws that provide substantially equivalent rights and remedies for alleged discriminatory housing practices. Objectives include provisions for strengthening existing or establishing new fair housing enforcement organizations. | G62: Project Grants | H62: Individual/Family,Minority group,Specialized group (e.g. health professionals, students, veterans) | I62: Local (includes State-designated lndian Tribes, excludes institutions of higher education and hospitals,Private nonprofit institution/organization (includes institutions of higher education and hospitals),Public nonprofit institution/organization (includes institutions of higher education and hospitals),State (includes District of Columbia, public institutions of higher education and hospitals) | J62: 0 | K62: 0 | L62: 0 | M62: [{"x":"2023","sam_estimate":0.0,"sam_actual":70610068.0,"usa_spending_actual":0.0},{"x":"2024","sam_estimate":0.0,"sam_actual":38945457.0,"usa_spending_actual":0.0},{"x":"2025","sam_estimate":0.0,"sam_actual":56000000.0,"usa_spending_actual":0.0}]
A63: 14.416 | B63: Education and Outreach Initiatives | C63: (FHIP EOI) Federal Agency Department of Housing and Urban Development - Office of Fair Housing and Equal Opportunity | D63: Department of Housing and Urban Development | E63: Assistant Secretary for Fair Housing and Equal Opportunity | F63: To assist organizations that are regional and local, community based and National programs, that develop, implement, carry out, or coordinate programs and/or activities to educate the public about their rights under, the Fair Housing Act (42 U.S.C. 3601-3619) or about State or local laws that provide substantially equivalent rights and remedies for alleged discriminatory housing practices. | G63: Project Grants | H63: Consumer,Disabled (e.g. Deaf, Blind, Physically Disabled),Homeowner,Individual/Family,Local,Mentally Disabled,Other public institution/organization,Public nonprofit institution/organization,State,Women | I63: Local (includes State-designated lndian Tribes, excludes institutions of higher education and hospitals,Private nonprofit institution/organization (includes institutions of higher education and hospitals),Public nonprofit institution/organization (includes institutions of higher education and hospitals),State (includes District of Columbia, public institutions of higher education and hospitals) | J63: 0 | K63: -40015.39 | L63: -143986.89 | M63: [{"x":"2023","sam_estimate":0.0,"sam_actual":9889619.0,"usa_spending_actual":-143986.89},{"x":"2024","sam_estimate":0.0,"sam_actual":10466207.0,"usa_spending_actual":-40015.39},{"x":"2025","sam_estimate":0.0,"sam_actual":9600000.0,"usa_spending_actual":0.0}]
A64: 14.417 | B64: Fair Housing Organization Initiatives | C64: (FHIP FHOI) Federal Agency Department of Housing and Urban Development - Office of Fair Housing and Equal Opportunity | D64: Department of Housing and Urban Development | E64: Assistant Secretary for Fair Housing and Equal Opportunity | F64: To assist organizations that are regional and local, community based and National programs, that develop, implement, carry out, or coordinate programs and/or activities to educate the public about their rights under, the Fair Housing Act (42 U.S.C. 3601-3619) or about State or local laws that provide substantially equivalent rights and remedies for alleged discriminatory housing practices. | G64: Project Grants | H64: Consumer,Disabled (e.g. Deaf, Blind, Physically Disabled),Homeowner,Individual/Family,Local,Mentally Disabled,Public nonprofit institution/organization,State,Women | I64: Local (includes State-designated lndian Tribes, excludes institutions of higher education and hospitals,Public nonprofit institution/organization (includes institutions of higher education and hospitals),State (includes District of Columbia, public institutions of higher education and hospitals) | J64: 0 | K64: 14136129 | L64: 13716086 | M64: [{"x":"2023","sam_estimate":0.0,"sam_actual":3750000.0,"usa_spending_actual":13716085.95},{"x":"2024","sam_estimate":0.0,"sam_actual":3700000.0,"usa_spending_actual":14136128.68},{"x":"2025","sam_estimate":0.0,"sam_actual":2700000.0,"usa_spending_actual":-3210.26}]
A65: 14.418 | B65: Private Enforcement Initiatives | C65: (FHIP PEI) United States Department of Housing and Urban Development - Office of Fair Housing and Equal Opportunity | D65: Department of Housing and Urban Development | E65: Assistant Secretary for Fair Housing and Equal Opportunity | F65: To assist private non-profit fair housing enforcement organizations in the investigation and enforcement of violations of the rights granted under title VIII of the Civil Rights Act of 1968 (42 U.S.C. 2801). To develop, implement, and carry out, related activities and enforcement under the Fair Housing Act or State or local laws that provide substantially equivalent rights and remedies for alleged discriminatory housing practices. Objectives include carrying out testing and other investigative activities. | G65: Project Grants | H65: Anyone/general public,Consumer,Disabled (e.g. Deaf, Blind, Physically Disabled),Homeowner,Individual/Family,Local,Mentally Disabled,Public nonprofit institution/organization,State,Women | I65: Anyone/general public,Individual/Family,Minority group,Public nonprofit institution/organization (includes institutions of higher education and hospitals),State | J65: 0 | K65: 24395901 | L65: 56409030 | M65: [{"x":"2023","sam_estimate":0.0,"sam_actual":56871449.0,"usa_spending_actual":56409029.59},{"x":"2024","sam_estimate":0.0,"sam_actual":24779250.0,"usa_spending_actual":24395900.54},{"x":"2025","sam_estimate":0.0,"sam_actual":42300000.0,"usa_spending_actual":10856025.93}]
A66: 14.506 | B66: General Research and Technology Activity | D66: Department of Housing and Urban Development | E66: Assistant Secretary for Policy Development and Research | F66: What all funding does this listing include? All Core R&T activities (per the PDR Congressional Justifications)? If so, the description/objective should be more broad to include discussion of the other work PDR does with these funds, e.g., Housing Data Infrastructure, Knowledge Management, Dissemination, and Outreach, research partnerships, etc. | G66: Project Grants | H66: Federal,Other private institution/organization,Private nonprofit institution/organization,Profit organization,Quasi-public nonprofit organization,Scientist/Researchers,Small business | I66: Federal,Profit organization,Quasi-public nonprofit institution/organization,Small business (less than 500 employees) | J66: 0 | K66: 5000000 | L66: 7583290 | M66: [{"x":"2023","sam_estimate":0.0,"sam_actual":20671649.0,"usa_spending_actual":7583290.03},{"x":"2024","sam_estimate":0.0,"sam_actual":20000000.0,"usa_spending_actual":5000000.0},{"x":"2025","sam_estimate":0.0,"sam_actual":0.0,"usa_spending_actual":400000.0}]
A67: 14.536 | B67: Research, Evaluation, and Demonstrations | D67: Department of Housing and Urban Development | E67: Assistant Secretary for Policy Development and Research | F67: This is a Notice of Funding Availability (NOFA) from the Department of Housing and Urban Development’s (HUD) for Research and Evaluation, Demonstrations. Through this NOFA, HUD plans to solicit applications for cooperative agreements to engage in research, evaluations, demonstrations activities. Funding will be available under three different categories or “functions”: Research and Evaluation; Demonstrations | G67: Project Grants | H67: Education Professional,Federal,Interstate,Local,Other private institution/organization,Other public institution/organization,Private nonprofit institution/organization,Profit organization,Public nonprofit institution/organization,Scientist/Researchers,Sponsored organization,State | I67: Federal,Government - General,Local (includes State-designated lndian Tribes, excludes institutions of higher education and hospitals,Private nonprofit institution/organization (includes institutions of higher education and hospitals),Profit organization,Public nonprofit institution/organization (includes institutions of higher education and hospitals),Small business (less than 500 employees),Sponsored organization,State (includes District of Columbia, public institutions of higher education and hospitals) | J67: 0 | K67: 3994529 | L67: 14854337 | M67: [{"x":"2023","sam_estimate":0.0,"sam_actual":20000000.0,"usa_spending_actual":14854336.57},{"x":"2024","sam_estimate":0.0,"sam_actual":15860000.0,"usa_spending_actual":3994529.02},{"x":"2025","sam_estimate":0.0,"sam_actual":0.0,"usa_spending_actual":0.0}]
A68: 14.537 | B68: Eviction Protection Grant Program | D68: Department of Housing and Urban Development | E68: Assistant Secretary for Policy Development and Research | F68: The overall purpose of the Eviction Protection Grant Program is to support experienced legal service providers, not limited to legal service corporations, in providing legal assistance at no cost to low-income tenants at risk of or subject to eviction. This grant program plays an integral role in helping individuals and families, including people of color who are disproportionately represented among those evicted, people with limited English proficiency and people with disabilities, avoid eviction or minimize the disruption and damage caused by the eviction process. | G68: Project Grants | I68: Federally Recognized lndian Tribal Governments,Government - General,Local (includes State-designated lndian Tribes, excludes institutions of higher education and hospitals,Other public institution/organization,Public nonprofit institution/organization (includes institutions of higher education and hospitals),Sponsored organization,State,State (includes District of Columbia, public institutions of higher education and hospitals) | J68: 0 | K68: 0 | L68: 0 | M68: [{"x":"2023","sam_estimate":0.0,"sam_actual":0.0,"usa_spending_actual":0.0},{"x":"2024","sam_estimate":0.0,"sam_actual":30000000.0,"usa_spending_actual":0.0},{"x":"2025","sam_estimate":0.0,"sam_actual":0.0,"usa_spending_actual":0.0}]
A69: 14.850 | B69: Public Housing Operating Fund | C69: Operating Subsidy Grant | D69: Department of Housing and Urban Development | E69: Assistant Secretary for Public and Indian Housing | F69: To provide and operate cost-effective, decent, safe and affordable dwellings for lower income families through an authorized local Public Housing Agency (PHA). | G69: Formula Grants | H69: Disabled (e.g. Deaf, Blind, Physically Disabled),Individual/Family,Low Income,Physically Afflicted (e.g. TB, Arthritis, Heart Disease),Senior Citizen (60+),Unemployed | I69: Local (includes State-designated lndian Tribes, excludes institutions of higher education and hospitals | J69: 0 | K69: 5.2479963e+09 | L69: 5.1199569e+09 | M69: [{"x":"2023","sam_estimate":0.0,"sam_actual":5049927941.0,"usa_spending_actual":5119956942.04},{"x":"2024","sam_estimate":0.0,"sam_actual":5475784000.0,"usa_spending_actual":5247996272.23},{"x":"2025","sam_estimate":0.0,"sam_actual":5050000000.0,"usa_spending_actual":1810948207.57}]
A70: 14.856 | B70: Lower Income Housing Assistance Program Section 8 Moderate Rehabilitation | C70: (Section 8 Housing Assistance Payments Program for Very Low Income Families-Moderate Rehabilitation) | D70: Department of Housing and Urban Development | E70: Assistant Secretary for Public and Indian Housing | F70: The Moderate Rehabilitation (Mod Rehab) program was designed in 1978 to be an expansion of the rental certificate program. The rental certificate program was initially amended to permit moderate levels of rehabilitation to upgrade and preserve the nation's housing stock. | G70: Direct Payments for a Specified Use | H70: Anyone/general public,Disabled (e.g. Deaf, Blind, Physically Disabled),Homeowner,Individual/Family,Low Income,Mentally Disabled,Moderate Income,Physically Afflicted (e.g. TB, Arthritis, Heart Disease),Private nonprofit institution/organization,Public nonprofit institution/organization,Refugee/Alien,Senior Citizen (60+),U.S. Citizen,Unemployed,Veteran/Service person/Reservist (including dependents,Welfare Recipient,Women | I70: Other public institution/organization | J70: 0 | K70: 80033607 | L70: 79095834 | M70: [{"x":"2023","sam_estimate":0.0,"sam_actual":78900000.0,"usa_spending_actual":79095834.0},{"x":"2024","sam_estimate":0.0,"sam_actual":92800000.0,"usa_spending_actual":80033607.0},{"x":"2025","sam_estimate":0.0,"sam_actual":0.0,"usa_spending_actual":9823503.0}]
A71: 14.862 | B71: Indian Community Development Block Grant Program | C71: ICDBG | D71: Department of Housing and Urban Development | E71: Assistant Secretary for Public and Indian Housing | F71: The purpose of the Indian Community Development Block Grant (ICDBG) program is the development of viable American Indian and Alaska Native communities, including the creation of decent housing, suitable living environments, and economic opportunities primarily for persons with low- and moderate-incomes. | G71: Project Grants | H71: Federally Recognized Indian Tribal Governments,Low Income,Moderate Income,Native American Organizations | I71: Federally Recognized lndian Tribal Governments,Native American Organizations (includes lndian groups, cooperatives, corporations, partnerships, associations) | J71: 0 | K71: 71242752 | L71: 1.0870707e+08 | M71: [{"x":"2023","sam_estimate":0.0,"sam_actual":100991638.0,"usa_spending_actual":108707070.86},{"x":"2024","sam_estimate":0.0,"sam_actual":72030085.0,"usa_spending_actual":71242752.42},{"x":"2025","sam_estimate":0.0,"sam_actual":150000000.0,"usa_spending_actual":50285716.0}]
A72: 14.865 | B72: Public and Indian Housing Indian Loan Guarantee Program | C72: Section 184 | D72: Department of Housing and Urban Development | E72: Assistant Secretary for Public and Indian Housing | F72: To provide access to sources of private financing so Native American families can become homeowners in Indian Country. | G72: Guaranteed / Insured Loans | H72: Federally Recognized Indian Tribal Governments,Local,Native American Organizations,Other private institution/organization,Private nonprofit institution/organization | I72: Federally Recognized lndian Tribal Governments,Local (includes State-designated lndian Tribes, excludes institutions of higher education and hospitals,Native American Organizations (includes lndian groups, cooperatives, corporations, partnerships, associations),Other private institutions/organizations,Private nonprofit institution/organization (includes institutions of higher education and hospitals) | J72: 0 | K72: 0 | L72: 0 | M72: [{"x":"2023","sam_estimate":0.0,"sam_actual":271054146.0,"usa_spending_actual":0.0},{"x":"2024","sam_estimate":0.0,"sam_actual":342157979.0,"usa_spending_actual":0.0},{"x":"2025","sam_estimate":0.0,"sam_actual":454000000.0,"usa_spending_actual":0.0}]
A73: 14.866 | B73: Demolition and Revitalization of Severely Distressed Public Housing | C73: (HOPE VI) | D73: Department of Housing and Urban Development | E73: Assistant Secretary for Public and Indian Housing | F73: Revitalization Grants enable PHAs to improve the living environment for public housing residents of severely distressed public housing projects through the demolition, substantial rehabilitation, reconfiguration, and/or replacement of severely distressed units; revitalize the sites on which severely distressed public housing projects are located and contribute to the improvement of the surrounding neighborhood; lessen isolation and reduce the concentration of low-income families; build sustainable mixed-income communities; and provide well-coordinated, results-based community and supportive services that directly complement housing redevelopment and that help residents to achieve self-sufficiency, young people to obtain educational excellence, and the community to secure a desirable quality of life. | G73: Project Grants | H73: Individual/Family,Low Income,Other Urban,Suburban | I73: Other public institution/organization | J73: 0 | K73: 1161135.7 | L73: 0 | M73: [{"x":"2023","sam_estimate":0.0,"sam_actual":0.0,"usa_spending_actual":0.0},{"x":"2024","sam_estimate":0.0,"sam_actual":0.0,"usa_spending_actual":1161135.73},{"x":"2025","sam_estimate":0.0,"sam_actual":0.0,"usa_spending_actual":0.0}]
A74: 14.867 | B74: Indian Housing Block Grants | C74: IHBG; Native American Housing Block Grant Program (NAHBG) | D74: Department of Housing and Urban Development | E74: Assistant Secretary for Public and Indian Housing | F74: The Indian Housing Block Grants (IHBG) program is authorized under the Native American Housing Assistance and Self-Determination Act of 1996 (25 U.S.C. §4101 et seq.) (NAHASDA). Regulations for the program, which are found at 24 CFR Part 1000, were written by HUD in negotiation with Tribes and Tribally Designated Housing Entities (TDHEs). The grants, which are awarded based on a formula to Tribes and TDHEs, fund a range of affordable housing activities that primarily benefit low-income American Indian and Alaska Native families living in Indian Country and include activities that: 1) assist and promote affordable housing activities to develop, maintain, and operate affordable housing in safe and healthy environments on Indian reservations and in other Indian areas for occupancy by low-income Indian families; 2) coordinate activities to provide housing for Indian tribes and their members and to promote self-sufficiency and their members; 3) plan for and integrate infrastructure resources for Indian tribes with housing development for Indian tribes. | G74: Formula Grants,Project Grants | H74: American Indian,Federally Recognized Indian Tribal Governments,Low Income,Minority group,Moderate Income | I74: Federally Recognized lndian Tribal Governments,Local (includes State-designated lndian Tribes, excludes institutions of higher education and hospitals,Minority group | J74: 0 | K74: 1.2563826e+09 | L74: 9.3578662e+08 | M74: [{"x":"2023","sam_estimate":0.0,"sam_actual":915882053.0,"usa_spending_actual":935786616.06},{"x":"2024","sam_estimate":0.0,"sam_actual":1257621361.0,"usa_spending_actual":1256382595.77},{"x":"2025","sam_estimate":0.0,"sam_actual":970000000.0,"usa_spending_actual":21003461.0}]
A75: 14.869 | B75: Title VI Federal Guarantees for Financing Tribal Housing Activities | C75: Title VI | D75: Department of Housing and Urban Development | E75: Assistant Secretary for Public and Indian Housing | F75: To provide access to sources of private financing to Indian Housing Block Grant recipients that want to finance additional grant-eligible affordable housing and related community development projects. | G75: Guaranteed / Insured Loans | H75: American Indian,Native American Organizations | I75: Federally Recognized lndian Tribal Governments | J75: 0 | K75: 0 | L75: 0 | M75: [{"x":"2023","sam_estimate":0.0,"sam_actual":8000000.0,"usa_spending_actual":0.0},{"x":"2024","sam_estimate":0.0,"sam_actual":10201175.0,"usa_spending_actual":0.0},{"x":"2025","sam_estimate":0.0,"sam_actual":20000000.0,"usa_spending_actual":0.0}]
A76: 14.870 | B76: Resident Opportunity and Supportive Services - Service Coordinators | C76: (ROSS Service Coordinators) | D76: Department of Housing and Urban Development | E76: Assistant Secretary for Public and Indian Housing | F76: To address the economic and housing self-sufficiency needs of public and Indian housing residents by providing grant-funded service coordinators who link residents to the supportive services they need in order to achieve economic and housing self-sufficiency; and for elderly/disabled residents to continue to age/reside in place and avoid costlier forms of care. | G76: Project Grants | H76: Disabled (e.g. Deaf, Blind, Physically Disabled),Federally Recognized Indian Tribal Governments,Individual/Family,Low Income,Mentally Disabled,Minority group,Moderate Income,Native American Organizations,Other private institution/organization,Other public institution/organization,Physically Afflicted (e.g. TB, Arthritis, Heart Disease),Public nonprofit institution/organization,Senior Citizen (60+),Sponsored organization,Unemployed,Veteran/Service person/Reservist (including dependents,Welfare Recipient,Women | I76: Federally Recognized lndian Tribal Governments,Native American Organizations (includes lndian groups, cooperatives, corporations, partnerships, associations),Other public institution/organization,Public nonprofit institution/organization (includes institutions of higher education and hospitals) | J76: 0 | K76: 652162 | L76: -3136190.8 | M76: [{"x":"2023","sam_estimate":0.0,"sam_actual":30556772.0,"usa_spending_actual":-3136190.77},{"x":"2024","sam_estimate":0.0,"sam_actual":39696716.0,"usa_spending_actual":652162.0},{"x":"2025","sam_estimate":0.0,"sam_actual":35000000.0,"usa_spending_actual":0.0}]
A77: 14.871 | B77: Section 8 Housing Choice Vouchers | D77: Department of Housing and Urban Development | E77: Assistant Secretary for Public and Indian Housing | F77: The housing choice voucher program is the federal government's major program for assisting very low-income families, the elderly, and the disabled to afford decent, safe, and sanitary housing in the private market. Since housing assistance is provided on behalf of the family or individual, participants are able to find their own housing, including single-family homes, townhouses and apartments. The participant is free to choose any housing that meets the requirements of the program and is not limited to units located in subsidized housing projects. The program serves the most economically vulnerable families in the country, including families with disabilities, elderly families, formerly homeless veterans, and families with children, through federal assistance voucher payments in the provision of meeting their rental housing needs. HUD regulations merged the former Section 8 Rental Voucher program (14.855) with the former Section 8 Certificate program (14.857). Section 502 of the Public Housing Reform Act states that a purpose of the legislation is "consolidating the voucher and certificate programs for rental assistance under Section 8 of the United States Housing Act of 1937 (the "USHA") into a single market-driven program that will assist in making tenant-based rental assistance more successful at helping low-income families obtain affordable housing and will increase housing choice for low-income families". The HCVP is administered by local public housing agencies (PHAs) authorized under State law to operate housing programs within an area or jurisdiction. The PHAs receive federal funds from the U.S. Department of Housing and Urban Development (HUD) to administer the voucher program. The PHA accepts a family’s application for rental assistance, selects the applicant family for admission, and issues the selected family a voucher confirming the family’s eligibility for assistance. The family must then find and lease a dwelling unit suitable to the family’s needs and desires in the private rental market. The PHAs sign Housing Assistant Payment contracts with the landlords, and housing subsidy is paid to the landlord directly by the PHA on behalf of the participating family. The family then pays the difference between the actual rent charged by the landlord and the amount subsidized by the program. Under certain circumstances, if authorized by the PHA, a family may use its voucher to purchase a modest home. | G77: Direct Payments for a Specified Use | H77: Anyone/general public,Individual/Family,Low Income,Minority group,Moderate Income,Other Urban,Refugee/Alien,Rural,Senior Citizen (60+),Suburban,U.S. Citizen,Unemployed,Veteran/Service person/Reservist (including dependents,Welfare Recipient,Women | I77: Other private institutions/organizations,Private nonprofit institution/organization (includes institutions of higher education and hospitals),Public nonprofit institution/organization (includes institutions of higher education and hospitals),State (includes District of Columbia, public institutions of higher education and hospitals) | J77: 0 | K77: 3.2528852e+10 | L77: 2.9977914e+10 | M77: [{"x":"2023","sam_estimate":0.0,"sam_actual":30225095115.0,"usa_spending_actual":29977913903.21},{"x":"2024","sam_estimate":0.0,"sam_actual":31732681456.0,"usa_spending_actual":32528852267.33},{"x":"2025","sam_estimate":0.0,"sam_actual":33625000000.0,"usa_spending_actual":10861519361.09}]
A78: 14.872 | B78: Public Housing Capital Fund | C78: (CFP) | D78: Department of Housing and Urban Development | E78: Assistant Secretary for Public and Indian Housing | F78: The Capital Fund provides funds annually to Public Housing Agencies (PHAs) for capital and management activities, including modernization and development of public housing. The Capital fund also permits PHAs to use Capital Funds for financing activities, including payments of debt service and customary financing costs, in standard PHA developments and in mixed-finance developments which include Public Housing. | G78: Formula Grants | H78: Low Income | I78: Local (includes State-designated lndian Tribes, excludes institutions of higher education and hospitals,State (includes District of Columbia, public institutions of higher education and hospitals) | J78: 0 | K78: 3.2658057e+09 | L78: 3.4417625e+09 | M78: [{"x":"2023","sam_estimate":0.0,"sam_actual":3192113014.0,"usa_spending_actual":3441762471.69},{"x":"2024","sam_estimate":0.0,"sam_actual":3188665925.0,"usa_spending_actual":3265805734.17},{"x":"2025","sam_estimate":0.0,"sam_actual":3200000000.0,"usa_spending_actual":7210310.0}]
A79: 14.873 | B79: Native Hawaiian Housing Block Grants | D79: Department of Housing and Urban Development | E79: Assistant Secretary for Public and Indian Housing | F79: To provide funds to carry out affordable housing activities, including rental assistance both on and off the Hawaiian home lands, for eligible low-income Native Hawaiians. | G79: Project Grants | H79: Specialized group (e.g. health professionals, students, veterans) | I79: Specialized group (e.g. health professionals, students, veterans) | J79: 0 | K79: 22300000 | L79: 22802307 | M79: [{"x":"2023","sam_estimate":0.0,"sam_actual":22802306.0,"usa_spending_actual":22802306.59},{"x":"2024","sam_estimate":0.0,"sam_actual":22300000.0,"usa_spending_actual":22300000.0},{"x":"2025","sam_estimate":0.0,"sam_actual":22300000.0,"usa_spending_actual":0.0}]
A80: 14.874 | B80: Loan Guarantees for Native Hawaiian Housing | C80: Section 184A | D80: Department of Housing and Urban Development | E80: Assistant Secretary for Public and Indian Housing | F80: To provide access to sources of private financing on Hawaiian home lands. | G80: Guaranteed / Insured Loans | H80: Individual/Family | I80: Individual/Family,Interstate,Private nonprofit institution/organization (includes institutions of higher education and hospitals),Quasi-public nonprofit institution/organization | J80: 0 | K80: 0 | L80: 0 | M80: [{"x":"2023","sam_estimate":0.0,"sam_actual":4924541.0,"usa_spending_actual":0.0},{"x":"2024","sam_estimate":0.0,"sam_actual":3271898.0,"usa_spending_actual":0.0},{"x":"2025","sam_estimate":0.0,"sam_actual":9000000.0,"usa_spending_actual":0.0}]
A81: 14.878 | B81: Affordable Housing Development in Main Street Rejuvenation Projects | C81: (Main Street) | D81: Department of Housing and Urban Development | E81: Assistant Secretary for Public and Indian Housing | F81: To assist small communities with populations of 50,000 or less and 100 Public Housing units or less in the rejuvenation of historic or traditional central business districts or "Main Street Areas" by replacing unused commercial space in buildings with Affordable housing units. The objectives of the program are to: (1) Redevelop Main Street Areas; (2) Preserve historic or traditional architecture or design features in Main Street Areas; (3) Enhance economic development efforts in Main Street Areas; and (4) Provide affordable housing in Main Street Areas. | G81: Project Grants | H81: Builder/Contractor/Developer,Individual/Family,Land/Property Owner,Local,Low Income,Other public institution/organization,Rural,Suburban,U.S. Territories | I81: Local (includes State-designated lndian Tribes, excludes institutions of higher education and hospitals | J81: 0 | K81: 0 | L81: 0 | M81: [{"x":"2023","sam_estimate":0.0,"sam_actual":0.0,"usa_spending_actual":0.0},{"x":"2024","sam_estimate":0.0,"sam_actual":2000000.0,"usa_spending_actual":0.0},{"x":"2025","sam_estimate":0.0,"sam_actual":0.0,"usa_spending_actual":0.0}]
A82: 14.879 | B82: Mainstream Vouchers | D82: Department of Housing and Urban Development | E82: Assistant Secretary for Public and Indian Housing | F82: The Mainstream Vouchers (previously referred to as the Mainstream 5-Year Program and/or the Section 811 Voucher Program) were originally authorized under the National Affordable Housing Act of 1990 (P.L. 101-625). The Mainstream Vouchers provides tenant-based assistance to persons with disabilities. Until the passage of the Frank Melville Supportive Housing Investment Act of 2010 (P.L. 111-374) (Melville Act), the program operated as a separate program distinct from the regular tenant-based Housing Choice Voucher Program. The Melville Act converted the Mainstream 5-Year Program to the Housing Choice Voucher (HCV) Program under 8(o) of the U.S. Housing Act of 1937. Under the Melville Act, except for serving a specific population, Mainstream vouchers are to be treated the same as regular voucher assistance. In other words, the same regulations at 24 CFR Part 982 (Section 8 Tenant-Based Assistance: Housing Choice Voucher Program) apply to Mainstream vouchers. There is no authority to treat families that receive a Mainstream voucher differently from other applicants and participants of the HCV program. After enactment of the Melville Act (i.e., subsequent to conversion of this assistance to section 8(o) voucher assistance), funding for Mainstream voucher renewals and administrative fees was first provided in the Consolidated and Further Continuing Appropriations Act, 2012 (P.L. 112-55) under its own paragraph under the Tenant-Based Rental Assistance (TBRA) heading. The Consolidated Appropriations Act, 2017 provided funding for incremental Mainstream vouchers for the first time since the enactment of the Melville Act (in addition to renewal and administrative fee funding). These incremental vouchers exclusively assisted non-elderly persons with disabilities. The Consolidated Appropriations Act, 2018 and the Consolidated Appropriations Act, 2019 ("2019 Act") also provided funding for incremental Mainstream vouchers for non-elderly persons with disabilities, in addition to renewal and administrative fee funding. In addition, the 2019 Act states that all new and existing Mainstream vouchers must be provided to non-elderly persons with disabilities upon turnover. Consistent with prior appropriations acts, all funding for 2017-2019 Mainstream vouchers was provided under its own paragraph (e.g., paragraph (4) under the TBRA heading in the 2019 Act). While the Melville Act requires Mainstream vouchers to be treated the same as regular voucher assistance, the separate HCV Mainstream appropriations results in an accounting of Mainstream activity separate from the HCV program. | G82: Direct Payments for a Specified Use | H82: Disabled (e.g. Deaf, Blind, Physically Disabled),Mentally Disabled | I82: State | J82: 0 | K82: 624803514 | L82: 717062072 | M82: [{"x":"2023","sam_estimate":0.0,"sam_actual":716993321.0,"usa_spending_actual":717062072.0},{"x":"2024","sam_estimate":0.0,"sam_actual":625709592.0,"usa_spending_actual":624803514.0},{"x":"2025","sam_estimate":0.0,"sam_actual":701000000.0,"usa_spending_actual":240504634.0}]
A83: 14.880 | B83: Family Unification Program (FUP) | D83: Department of Housing and Urban Development | E83: Assistant Secretary for Public and Indian Housing | F83: To aid: (1) Families for whom the lack of adequate housing is a primary factor in: a. The imminent placement of the family’s child or children in out-of-home care, or b. The delay in the discharge of the child or children to the family from out-of-home care. (2) For a period not to exceed 36 months, otherwise eligible youths who have attained at least 18 years and not more than 24 years of age and who have left foster care, or will leave foster care within 90 days, in accordance with a transition plan described in section 475(5)(H) of the Social Security Act and is homeless or is at risk of becoming homeless at age 16 or older. FUP- eligible families and youths may use these Housing Choice Vouchers (HVCs) to obtain decent, safe, and affordable housing units in the private rental market. Where appropriations provide for FUP assistance to be targeted to FUP-eligible youth only, HUD uses the name Foster Youth to Independence to create a distinction between regular FUP allocations and allocations targeted to FUP-eligible youth only. | G83: Direct Payments for a Specified Use | H83: Individual/Family,Low Income,Refugee/Alien,U.S. Citizen,Unemployed,Veteran/Service person/Reservist (including dependents,Welfare Recipient,Women | I83: Public nonprofit institution/organization (includes institutions of higher education and hospitals),State (includes District of Columbia, public institutions of higher education and hospitals) | J83: 0 | K83: -1252495.9 | L83: -518570.68 | M83: [{"x":"2023","sam_estimate":0.0,"sam_actual":39000000.0,"usa_spending_actual":-518570.68},{"x":"2024","sam_estimate":0.0,"sam_actual":0.0,"usa_spending_actual":-1252495.87},{"x":"2025","sam_estimate":0.0,"sam_actual":0.0,"usa_spending_actual":0.0}]
A84: 14.881 | B84: Moving to Work Demonstration Program | D84: Department of Housing and Urban Development | E84: Assistant Secretary for Public and Indian Housing | F84: Moving to Work (MTW) is a demonstration program for public housing authorities (PHAs) that provides opportunities to design and test innovative, locally designed strategies that use Federal dollars more efficiently, help residents find employment and become self-sufficient, and increase housing choices for low-income families. MTW allows PHAs exemptions from many existing public housing and voucher rules and provides funding flexibility with how they use their Federal funds. | G84: Formula Grants | H84: Low Income | I84: Local (includes State-designated lndian Tribes, excludes institutions of higher education and hospitals | J84: 0 | K84: 0 | L84: 0 | M84: [{"x":"2023","sam_estimate":0.0,"sam_actual":0.0,"usa_spending_actual":0.0},{"x":"2024","sam_estimate":0.0,"sam_actual":0.0,"usa_spending_actual":0.0},{"x":"2025","sam_estimate":0.0,"sam_actual":0.0,"usa_spending_actual":0.0}]
A85: 14.888 | B85: Lead-Based Paint Capital Fund Program | C85: Lead-based Paint (LBP) and Other Housing-Related Hazards (HRH) Combined NOFO | D85: Department of Housing and Urban Development | E85: Assistant Secretary for Public and Indian Housing | F85: The Lead-Based Paint and Housing-Related Hazards are for Public Housing Authorities (PHAs) to evaluate and reduce lead-based paint and other housing-related hazards including carbon monoxide and mold in public housing, and for other costs associated with public housing asset improvement. The Lead-Based Paint Capital Fund Program provides competitive grants to PHAs to evaluate and reduce lead-based paint hazards in public housing by carrying out the activities of risk assessments, abatement, and interim controls (as those terms are defined in section 1004 of the Residential Lead-Based Paint Hazard Reduction Act of 1992 (42 U.S.C. 4851b)). The Housing-Related Hazards Capital Fund Program provides funds for PHAs to prevent and correct significant housing-related health and safety hazards such as mold and carbon monoxide in public housing. | G85: Project Grants | H85: Individual/Family,Low Income | I85: Other public institution/organization | J85: 0 | K85: 45634890 | L85: 34752420 | M85: [{"x":"2023","sam_estimate":0.0,"sam_actual":150925165.0,"usa_spending_actual":34752420.0},{"x":"2024","sam_estimate":0.0,"sam_actual":87740890.0,"usa_spending_actual":45634890.0},{"x":"2025","sam_estimate":0.0,"sam_actual":65000000.0,"usa_spending_actual":0.0}]
A86: 14.889 | B86: Choice Neighborhoods Implementation Grants | D86: Department of Housing and Urban Development | E86: Assistant Secretary for Public and Indian Housing | F86: Choice Neighborhoods Implementation Grants provide funds to implement comprehensive plans for community revitalization centered on redeveloping severely distressed public housing and/or HUD-assisted housing. The program aims to transform neighborhoods of poverty into viable mixed-income neighborhoods by revitalizing a target housing projects and catalyzing critical improvements in the neighborhood, including commercial and retail development, recreational amenities, social services and improved educational opportunities. | G86: Project Grants | H86: Anyone/general public,Local,Low Income,Moderate Income,Private nonprofit institution/organization | I86: Local (includes State-designated lndian Tribes, excludes institutions of higher education and hospitals,Private nonprofit institution/organization (includes institutions of higher education and hospitals),Profit organization | J86: 0 | K86: 3.348802e+08 | L86: 429625956 | M86: [{"x":"2023","sam_estimate":0.0,"sam_actual":468216956.0,"usa_spending_actual":429625956.0},{"x":"2024","sam_estimate":0.0,"sam_actual":327500000.0,"usa_spending_actual":334880204.6},{"x":"2025","sam_estimate":0.0,"sam_actual":130000000.0,"usa_spending_actual":0.0}]
A87: 14.892 | B87: Choice Neighborhoods Planning Grants | D87: Department of Housing and Urban Development | E87: Assistant Secretary for Public and Indian Housing | F87: Choice Neighborhoods Planning Grants support the development of comprehensive neighborhood Transformation Plans which are centered on the revitalization of a severely distressed public housing or HUD-assisted housing project. The Transformation Plan should integrate effective strategies for redevelopment of the targeted public and/or assisted housing project; the provision of supportive services for housing residents which address employment, health and educational opportunities; and initiatives which improve the range of neighborhood assets and promote economic development. The Transformation Plan should be created as part of a collaborative planning process that involves neighborhood stakeholders, local governmental entities and residents, and builds the necessary support to successfully implement the plan. | G87: Project Grants | H87: Anyone/general public,Individual/Family,Local,Other private institution/organization,Other public institution/organization,Private nonprofit institution/organization,Profit organization,Public nonprofit institution/organization,Small Business Person,U.S. Citizen | I87: Other public institution/organization,Private nonprofit institution/organization (includes institutions of higher education and hospitals),Profit organization,Public nonprofit institution/organization (includes institutions of higher education and hospitals),State | J87: 0 | K87: 1000000 | L87: 0 | M87: [{"x":"2023","sam_estimate":0.0,"sam_actual":7000000.0,"usa_spending_actual":0.0},{"x":"2024","sam_estimate":0.0,"sam_actual":6500000.0,"usa_spending_actual":1000000.0},{"x":"2025","sam_estimate":0.0,"sam_actual":10000000.0,"usa_spending_actual":0.0}]
A88: 14.893 | B88: Office of Native American Programs Training and Technical Assistance for Indian Housing Block Grant Program | D88: Department of Housing and Urban Development | E88: Assistant Secretary for Public and Indian Housing | F88: To provide technical assistance for Indian tribes, Alaska Native villages, and Tribally Designated Housing Entities (TDHEs) in the development of viable communities. | G88: Training | H88: American Indian,Federally Recognized Indian Tribal Governments,Native American Organizations | I88: Federally Recognized lndian Tribal Governments,Minority group,Native American Organizations (includes lndian groups, cooperatives, corporations, partnerships, associations),Other private institutions/organizations,Other public institution/organization,Private nonprofit institution/organization (includes institutions of higher education and hospitals),Profit organization,Public nonprofit institution/organization (includes institutions of higher education and hospitals),Quasi-public nonprofit institution/organization,Small business (less than 500 employees) | J88: 0 | K88: 0 | L88: 0 | M88: [{"x":"2023","sam_estimate":0.0,"sam_actual":20264143.0,"usa_spending_actual":0.0},{"x":"2024","sam_estimate":0.0,"sam_actual":0.0,"usa_spending_actual":0.0},{"x":"2025","sam_estimate":0.0,"sam_actual":14000000.0,"usa_spending_actual":0.0}]
A89: 14.895 | B89: Jobs-Plus Pilot Initiative | C89: Jobs-Plus Iniative | D89: Department of Housing and Urban Development | E89: Assistant Secretary for Public and Indian Housing | F89: The Jobs Plus program develops locally based, job-driven approaches that increase earnings and advance employment outcomes through work readiness, employer linkages, job placement, educational advancement, technology skills, and financial literacy for residents of public housing. The place-based Jobs Plus program addresses poverty among public housing residents by incentivizing and enabling employment through earned income disregards for working residents and a set of services designed to support work including employer linkages, job placement and counseling, educational advancement, and financial counseling. Ideally, these incentives will saturate the target public housing development, building a culture of work and making working residents the norm. The Jobs Plus program model comprises these three core components: Employment-Related Services; Financial/Rent Incentive – Jobs Plus Earned Income Disregard (JPEID); and Community Supports for Work. | G89: Project Grants | H89: Local,Low Income,State,U.S. Citizen,Unemployed | I89: Government - General,State | J89: 0 | K89: 69718826 | L89: 39690075 | M89: [{"x":"2023","sam_estimate":0.0,"sam_actual":9199059.0,"usa_spending_actual":39690074.99},{"x":"2024","sam_estimate":0.0,"sam_actual":30934403.0,"usa_spending_actual":69718825.79},{"x":"2025","sam_estimate":0.0,"sam_actual":15000000.0,"usa_spending_actual":0.0}]
A90: 14.896 | B90: Family Self-Sufficiency Program | C90: (FSS) | D90: Department of Housing and Urban Development | E90: Assistant Secretary for Public and Indian Housing | F90: To promote the development of local strategies to coordinate the use of assistance under the Housing Choice Voucher, Public Housing and Project-Based Rental Assistance programs with public and private resources to enable participating families to increase earned income and financial literacy, reduce or eliminate the need for welfare assistance, and make progress toward economic independence and self-sufficiency. Public Housing FSS and HCV FSS were separate programs for many years. They were combined into one FSS program in FY14. PBRA became eligible to be funded with the implementation of the FSS Final Rule in May 2022. | G90: Project Grants | H90: Individual/Family,Low Income | I90: Government - General,Profit organization,Public nonprofit institution/organization (includes institutions of higher education and hospitals),State | J90: 0 | K90: 1.2168253e+08 | L90: 1.1168677e+08 | M90: [{"x":"2023","sam_estimate":0.0,"sam_actual":114992550.0,"usa_spending_actual":111686771.58},{"x":"2024","sam_estimate":0.0,"sam_actual":132673160.0,"usa_spending_actual":121682530.39},{"x":"2025","sam_estimate":0.0,"sam_actual":125000000.0,"usa_spending_actual":-3391263.95}]
A91: 14.899 | B91: Tribal HUD-VA Supportive Housing Program | C91: Tribal HUD-VASH | D91: Department of Housing and Urban Development | E91: Assistant Secretary for Public and Indian Housing | F91: The Tribal HUD-VASH program combines rental assistance from the Department of Housing and Urban Development (HUD) with supportive services provided by the Department of Veterans Affairs to Native American Veterans who are homeless or at risk of homelessness. | G91: Project Grants | H91: American Indian,Federally Recognized Indian Tribal Governments,Individual/Family,Low Income,Minority group,Native American Organizations,Specialized group (e.g. health professionals, students, veterans),Unemployed,Veteran/Service person/Reservist (including dependents | I91: Government - General | J91: 0 | K91: 0 | L91: 0 | M91: [{"x":"2023","sam_estimate":0.0,"sam_actual":10260580.0,"usa_spending_actual":0.0},{"x":"2024","sam_estimate":0.0,"sam_actual":9987212.0,"usa_spending_actual":0.0},{"x":"2025","sam_estimate":0.0,"sam_actual":5000000.0,"usa_spending_actual":0.0}]
A92: 14.900 | B92: Lead Hazard Reduction Grant Program | C92: Lead Hazard Reduction Grant Program | D92: Department of Housing and Urban Development | E92: Office of Lead Hazard Control and Healthy Homes | F92: Lead-Based Paint Hazard Control grants assist State, Tribal, and local governments to identify and control lead-based paint hazards in privately-owned housing that is owned by or rented to low- or very-low income families. Specific objectives include: (1) Maximize the combination of children less than six years of age protected from lead poisoning and housing units where lead-hazards are controlled; (2) Prevent childhood lead poisoning; (3) Stimulate lower-cost and cost-effective methods and approaches to lead hazard control work that can be replicated; (4) Build local capacity to safely and effectively address lead hazards during lead hazard control, renovation, remodeling, and maintenance activities by integrating lead safe work practices into housing maintenance, repair, weatherization, rehabilitation and other programs that will continue beyond the grant period; (5) Affirmatively further fair housing and environmental justice (6) Develop a comprehensive community approach to address lead hazards in housing by mobilizing public and private resources, involving cooperation among all levels of government, the private sector, and grassroots community-based nonprofit organizations, including faith-based organizations, to develop cost-effective methods for identifying and controlling lead-based paint hazards (7) Establish a public registry of lead-safe housing; and (8)To the greatest extent feasible, promote job training, employment, and other economic opportunities for low-income and minority residents and businesses that are owned by and/or employ minorities and low-income persons as defined in 24 CFR section 75.5. | G92: Project Grants | H92: Anyone/general public,Federal,Individual/Family,Local,State | I92: Federally Recognized lndian Tribal Governments,Local (includes State-designated lndian Tribes, excludes institutions of higher education and hospitals,State (includes District of Columbia, public institutions of higher education and hospitals) | J92: 0 | K92: 1.7673889e+08 | L92: 1.8580003e+08 | M92: [{"x":"2023","sam_estimate":0.0,"sam_actual":20767732.0,"usa_spending_actual":185800027.99},{"x":"2024","sam_estimate":0.0,"sam_actual":204999998.0,"usa_spending_actual":176738888.22},{"x":"2025","sam_estimate":0.0,"sam_actual":0.0,"usa_spending_actual":5467900.78}]
A93: 14.901 | B93: Healthy Homes Weatherization Cooperation Demonstration Grants | C93: Healthy Homes and Weatherization Cooperation Demonstration Grants, Radon Testing and Mitigation Demonstration in Public Housing Grants | D93: Department of Housing and Urban Development | E93: Office of Lead Hazard Control and Healthy Homes | F93: HUD, through this Healthy Homes and Weatherization Cooperation Demonstration (HHWCD) NOFO, is interested in supporting demonstrations in up to 5 communities that provide housing interventions in lower-income households that are conducted jointly through the coordination of HUD’s Office of Lead Hazard Control and Healthy Homes (OLHCHH)-funded Healthy Homes Production (HHP) program and programs funded by the U.S. Department of Energy's (DOE) Weatherization Assistance Program (WAP). A critical goal of this demonstration is to determine whether this coordinated delivery of services achieves cost-effectiveness and better outcomes in improving the safety and quality of homes, including health and energy efficiency. The coordinated assessments and interventions are expected to provide additional benefits to households through the combined mitigation of health and safety hazards and improvements in energy efficiency and comfort. These grants are intended to facilitate the leveraging of ass | G93: Project Grants | H93: Anyone/general public,Federally Recognized Indian Tribal Governments,Homeowner,Land/Property Owner,Local,Minority group,Public nonprofit institution/organization,State,U.S. Territories | I93: Federally Recognized lndian Tribal Governments,Government - General,Non-Government - General,State,U.S. Territories and possessions | J93: 0 | K93: 6187462.2 | L93: 4953526 | M93: [{"x":"2023","sam_estimate":0.0,"sam_actual":5953526.0,"usa_spending_actual":4953526.0},{"x":"2024","sam_estimate":0.0,"sam_actual":7000000.0,"usa_spending_actual":6187462.16},{"x":"2025","sam_estimate":0.0,"sam_actual":0.0,"usa_spending_actual":0.0}]
A94: 14.902 | B94: Lead Technical Studies Grants | C94: Lead Technical Studies Grants | D94: Department of Housing and Urban Development | E94: Office of Lead Hazard Control and Healthy Homes | F94: To fund technical studies to improve methods for detecting and controlling lead-based paint hazards in housing. The purpose of the Lead Technical Studies program is to improve our knowledge of lead-based paint related health hazards, and to improve or develop new hazard assessment and control methods. | G94: Project Grants | H94: Homeowner,Land/Property Owner | I94: Federally Recognized lndian Tribal Governments,Local (includes State-designated lndian Tribes, excludes institutions of higher education and hospitals,Public nonprofit institution/organization (includes institutions of higher education and hospitals),State (includes District of Columbia, public institutions of higher education and hospitals) | J94: 0 | K94: 5553572.9 | L94: -12171.74 | M94: [{"x":"2023","sam_estimate":0.0,"sam_actual":2000000.0,"usa_spending_actual":-12171.74},{"x":"2024","sam_estimate":0.0,"sam_actual":1500000.0,"usa_spending_actual":5553572.87},{"x":"2025","sam_estimate":0.0,"sam_actual":0.0,"usa_spending_actual":0.0}]
A95: 14.905 | B95: Lead Hazard Reduction Demonstration Grant Program | C95: Lead Hazard Reduction Demonstration Grant Program | D95: Department of Housing and Urban Development | E95: Office of Lead Hazard Control and Healthy Homes | F95: Lead Hazard Reduction Demonstration Grant assist State, Tribal, and local governments to identify and control lead-based paint hazards in privately-owned housing that is owned by or rented to low- or very-low income families. Specific objectives include: (1) Maximize the combination of children less than six years of age protected from lead poisoning and housing units where lead-hazards are controlled; (2) preventing childhood lead poisoning; (3) Stimulate lower-cost and cost-effective methods and approaches to lead hazard control work that can be replicated; (4)Build local capacity to safely and effectively address lead hazards during lead hazard control, renovation, remodeling, and maintenance activities by integrating lead safe work practices into housing maintenance, repair, weatherization, rehabilitation and other programs that will continue beyond the grant period; (5) Affirmatively further fair housing and environmental justice (6) Develop a comprehensive community approach to address lead hazards in housing by mobilizing public and private resources, involving cooperation among all levels of government, the private sector, and grassroots community-based nonprofit organizations, including faith-based organizations, to develop cost-effective methods for identifying and controlling lead-based paint hazards (7) establishing a public registry of lead-safe housing; and (8) To the greatest extent feasible, promote job training, employment, and other economic opportunities for low-income and minority residents and businesses that are owned by and/or employ minorities and low-income persons as defined in 24 CFR 75.5 . In addition to the requirements above, you must have at least 3,500 pre-1940 occupied rental housing units (either alone or through a consortium). | G95: Project Grants | H95: Anyone/general public,Federal,Individual/Family,Local,State | I95: Federally Recognized lndian Tribal Governments,Local (includes State-designated lndian Tribes, excludes institutions of higher education and hospitals,State (includes District of Columbia, public institutions of higher education and hospitals) | J95: 0 | K95: 2.8724872e+08 | L95: -13764557 | M95: [{"x":"2023","sam_estimate":0.0,"sam_actual":102369748.0,"usa_spending_actual":-13764556.86},{"x":"2024","sam_estimate":0.0,"sam_actual":129000000.0,"usa_spending_actual":287248721.08},{"x":"2025","sam_estimate":0.0,"sam_actual":0.0,"usa_spending_actual":-1433539.35}]
A96: 14.906 | B96: Healthy Homes Technical Studies Grants | C96: Healthy Homes Technical Studies Grants | D96: Department of Housing and Urban Development | E96: Office of Lead Hazard Control and Healthy Homes | F96: To fund technical studies to improve methods for detecting and controlling housing-related health and safety hazards. The purpose of the Healthy Homes Technical Studies program is to improve our knowledge of housing-related health hazards, and to improve or develop new hazard assessment and control methods. | G96: Project Grants | H96: Federal,Local,Other public institution/organization,Profit organization,Public nonprofit institution/organization,State | I96: Federally Recognized lndian Tribal Governments,Local (includes State-designated lndian Tribes, excludes institutions of higher education and hospitals,Other public institution/organization,Public nonprofit institution/organization (includes institutions of higher education and hospitals),State (includes District of Columbia, public institutions of higher education and hospitals) | J96: 0 | K96: 0 | L96: 0 | M96: [{"x":"2023","sam_estimate":0.0,"sam_actual":5000000.0,"usa_spending_actual":0.0},{"x":"2024","sam_estimate":0.0,"sam_actual":5000000.0,"usa_spending_actual":0.0},{"x":"2025","sam_estimate":0.0,"sam_actual":0.0,"usa_spending_actual":0.0}]
A97: 14.912 | B97: Lead Hazard Control Capacity Building | C97: Lead Hazard Control Capacity Building | D97: Department of Housing and Urban Development | E97: Office of Lead Hazard Control and Healthy Homes | F97: The purpose of the Lead Hazard Reduction Capacity Building Grant Program is to assist states, Federally-recognized Native American Tribes, cities, counties/parishes, or other units of local government which have not received a HUD lead hazard control grant or been a sub-recipient of such a grant in developing the infrastructure necessary to undertake comprehensive programs to identify and control lead-based paint hazards in eligible privately owned rental or owner-occupied housing. | G97: Project Grants | H97: Federal,Local,State | I97: Federally Recognized lndian Tribal Governments,Local (includes State-designated lndian Tribes, excludes institutions of higher education and hospitals,State (includes District of Columbia, public institutions of higher education and hospitals) | J97: 0 | K97: 0 | L97: 0 | M97: [{"x":"2023","sam_estimate":0.0,"sam_actual":16363920.0,"usa_spending_actual":0.0},{"x":"2024","sam_estimate":0.0,"sam_actual":10000000.0,"usa_spending_actual":0.0},{"x":"2025","sam_estimate":0.0,"sam_actual":0.0,"usa_spending_actual":0.0}]
A98: 14.913 | B98: Healthy Homes Production Program | C98: Healthy Homes Production Grant Program | D98: Department of Housing and Urban Development | E98: Office of Lead Hazard Control and Healthy Homes | F98: The purpose of the Healthy Homes Production Program is to comprehensively address multiple residential health and safety hazards, including mold, carbon monoxide, home safety hazards, pesticides and allergens (from pets and pests). | G98: Project Grants | H98: Homeowner,Low Income | I98: Federally Recognized lndian Tribal Governments,Local (includes State-designated lndian Tribes, excludes institutions of higher education and hospitals,Private nonprofit institution/organization (includes institutions of higher education and hospitals),Profit organization,Public nonprofit institution/organization (includes institutions of higher education and hospitals),State,State (includes District of Columbia, public institutions of higher education and hospitals) | J98: 0 | K98: 0 | L98: 0 | M98: [{"x":"2023","sam_estimate":0.0,"sam_actual":17000000.0,"usa_spending_actual":0.0},{"x":"2024","sam_estimate":0.0,"sam_actual":45000000.0,"usa_spending_actual":0.0},{"x":"2025","sam_estimate":0.0,"sam_actual":0.0,"usa_spending_actual":0.0}]
A99: 14.914 | B99: Radon Interventions in Public and Assisted Multifamily Housing | D99: Department of Housing and Urban Development | E99: Office of Lead Hazard Control and Healthy Homes | F99: None. The program is defunct | G99: Project Grants | H99: Low Income | I99: Federally Recognized lndian Tribal Governments,Local (includes State-designated lndian Tribes, excludes institutions of higher education and hospitals,Other public institution/organization,Private nonprofit institution/organization (includes institutions of higher education and hospitals),Profit organization,Public nonprofit institution/organization (includes institutions of higher education and hospitals),State (includes District of Columbia, public institutions of higher education and hospitals) | J99: 0 | K99: 0 | L99: 0 | M99: [{"x":"2023","sam_estimate":0.0,"sam_actual":0.0,"usa_spending_actual":0.0},{"x":"2024","sam_estimate":0.0,"sam_actual":0.0,"usa_spending_actual":0.0},{"x":"2025","sam_estimate":0.0,"sam_actual":0.0,"usa_spending_actual":0.0}]
A100: 14.920 | B100: Lead Hazard Control for High Risk Areas | C100: Lead Risk Assessment Demonstration | D100: Department of Housing and Urban Development | E100: Office of Lead Hazard Control and Healthy Homes | F100: This funding will be made available to public housing agencies that operate the housing choice voucher program to conduct lead hazard screenings or lead-risk assessments during housing quality standards inspections of pre-1978 units in which a family with a voucher resides or expects to reside, and has or expects to have a child under age 6 residing in the unit, to demonstrate whether such a process preserves rental housing availability and affordability. | G100: Project Grants | H100: Low Income | I100: Local (includes State-designated lndian Tribes, excludes institutions of higher education and hospitals,State | J100: 0 | K100: 0 | L100: 600000 | M100: [{"x":"2023","sam_estimate":0.0,"sam_actual":600000.0,"usa_spending_actual":600000.0},{"x":"2024","sam_estimate":0.0,"sam_actual":0.0,"usa_spending_actual":0.0},{"x":"2025","sam_estimate":0.0,"sam_actual":0.0,"usa_spending_actual":0.0}]
A101: 14.921 | B101: Older Adults Home Modification Grant Program | D101: Department of Housing and Urban Development | E101: Office of Lead Hazard Control and Healthy Homes | F101: The purpose of the Older Adults Home Modification Grant Program is to enhance local capacity to sustainably operate low-barrier, participant-led programs that address the home modification needs of low-income older persons and their caregivers. | G101: Project Grants | H101: Individual/Family,Low Income,Rural | I101: Government - General,Local (includes State-designated lndian Tribes, excludes institutions of higher education and hospitals,Private nonprofit institution/organization (includes institutions of higher education and hospitals),Public nonprofit institution/organization (includes institutions of higher education and hospitals),State,State (includes District of Columbia, public institutions of higher education and hospitals) | J101: 0 | K101: 10000000 | L101: 0 | M101: [{"x":"2023","sam_estimate":0.0,"sam_actual":30000000.0,"usa_spending_actual":0.0},{"x":"2024","sam_estimate":0.0,"sam_actual":30000000.0,"usa_spending_actual":10000000.0},{"x":"2025","sam_estimate":0.0,"sam_actual":0.0,"usa_spending_actual":0.0}]

Sheet Matched Programs
A1: PDF Page (HUD) | B1: Program Name (HUD) | C1: Program Title (FPI) | D1: Administering Office (HUD) | E1: Sub-Agency (FPI) | F1: Program Summary (HUD) | G1: Statutory Authority (HUD) | H1: CFR Citation (HUD) | I1: Program Website(s) (HUD) | J1: AL Number (FPI) | K1: Popular Name (FPI) | L1: Objective (FPI) | M1: Assistance Types (FPI) | N1: Beneficiary Types (FPI) | O1: Applicant Types (FPI) | P1: FY2025 Obligation — FPI Headline ($, SAM est.) (FPI) | Q1: FY2024 Obligation ($, USAspending actual) (FPI) | R1: FY2023 Obligation ($, USAspending actual) (FPI) | S1: Income Test Type | T1: Statutory Family | U1: Governing Provision (income rule) | V1: Permitted Income Definition(s) | W1: Mandatory or Grantee Choice | X1: VA Comp — Income Eligibility | Y1: VA Comp — Rent / Assistance Amount | Z1: Eligibility Treatment vs. PL 119-70 §2 | AA1: Legal Basis for VA Treatment | AB1: Why (rationale) | AC1: Notes & Caveats | AD1: Verification Status
A2: MATCHED PROGRAMS (87 pairs — one row per HUD/FPI match; a HUD program that covers several FPI sub-listings appears once per sub-listing)
A3: 8 | B3: Capacity Building for Community Development and Affordable Housing (Section 4) | C3: Section 4 Capacity Building for Community Development and Affordable Housing | D3: Community Planning and Development (CPD) | E3: Assistant Secretary for Community Planning and Development | F3: Grants to national intermediaries to develop the capacity and ability of community development corporations (CDCs) and community housing development organizations (CHDOs) to carry out community development and affordable housing activities that benefit low- and moderateincome families and persons. | G3: Section 4 of the HUD Demonstration Act of 1993 (42 U.S.C. 9816 note). | I3: https://www.hud.gov/program_offices/comm_planning/section-4 | J3: 14.252 | K3: Section 4 Capacity Building | L3: The Section 4 program builds the capacity of Community Development Corporations (CDCs) and Community Housing Development Organizations (CHDOs) to serve their communities and low- and moderate-income families with community development and affordable housing activities. | M3: Project Grants | N3: Private nonprofit institution/organization | O3: Other private institutions/organizations | P3: 0 | Q3: 83000000 | R3: 41000000 | S3: Not income-tested | T3: Other statutes & appropriations | U3: — | V3: N/A | W3: N/A | X3: Not applicable | Y3: Not applicable | Z3: =IF(X3="","",IF(X3="Excluded","Consistent",IF(X3="Counted","Inconsistent",IF(X3="Varies (grantee/agency choice)","Partly inconsistent",IF(X3="Not applicable","Not applicable","Needs check"))))) | AA3: No household income eligibility test: grants to national intermediaries for capacity building (HUD Demonstration Act of 1993 §4). | AB3: Not a means-tested household benefit. | AD3: Not verified — low risk (not income-tested)
A4: 9 | B4: Community Development Block Grant Disaster Recovery (CDBG-DR) Assistance | C4: Hurricane Sandy Community Development Block Grant Disaster Recovery Grants (CDBG-DR) | D4: Community Planning and Development (CPD) | E4: Assistant Secretary for Community Planning and Development | F4: Flexible grants to help the most impacted and distressed areas recover long-term after Presidentially declared disasters. | G4: CDBG-DR assistance is largely governed by specific appropriations acts, most recently Public Law 117-328, and it is also subject to provisions of Title I of the Housing and Community Development Act of 1974 (42 U.S.C. 5301, et seq.) (made applicable by appropriations acts unless waived) and certain provisions of the Robert T. Stafford Disaster Relief and Emergency Assistance Act (42 U.S.C. 5121, et seq.). | I4: https://www.hud.gov/program_offices/comm_planning/cdbg-dr | J4: 14.269 | K4: Community Development Block Grant Disaster Recovery program for Hurricane Sandy and other qualifying disasters occurring in 2011, 2012 and 2013 | L4: The overall CDBG program objective is to develop viable urban communities, by providing decent housing and a suitable living environment, and by expanding economic opportunities, principally for persons of low and moderate income. CDBG DR program funds appropriated by P.L. 113-2 are for necessary expenses related to disaster relief, long-term recovery, restoration of infrastructure and housing, and economic revitalization in the most impacted and distressed areas resulting from a major disaster declaration due to Hurricane Sandy and other eligible events in calendar years 2011, 2012, and 2013. | M4: Formula Grants | N4: Homeowner,Individual/Family,Low Income,Moderate Income,Private nonprofit institution/organization,Public nonprofit institution/organization,Small business | O4: Local (includes State-designated lndian Tribes, excludes institutions of higher education and hospitals,State,U.S. Territories and possessions | P4: 0 | Q4: -140842.94 | R4: -1 | S4: Household income test | T4: HCDA Title I (CDBG family) | U4: 42 U.S.C. 5302(a)(20)(C) (added by PL 119-70 §2); 24 CFR 570.3 'Income' | V4: Part 5 / Census long-form / IRS 1040 AGI (grantee picks per activity) | W4: Grantee menu | X4: Excluded | Y4: Not applicable | Z4: =IF(X4="","",IF(X4="Excluded","Consistent",IF(X4="Counted","Inconsistent",IF(X4="Varies (grantee/agency choice)","Partly inconsistent",IF(X4="Not applicable","Not applicable","Needs check"))))) | AA4: PL 119-70 §2 (Jan. 20, 2026) requires a State, unit of general local government, or Indian tribe to exclude VA service-connected disability compensation when determining whether a person is low/moderate income. HUD implemented it sub-regulatorily in Notice CPD-26-09 (posted Sept. 4, 2026). 24 CFR 570.3 has not been amended: its Census option still lists 'Veterans' (VA) payments' as income. | AB4: HCDA sets income limits (80% AMI) but left the income definition to HUD, which offered a three-definition menu (1995) to ease local administration. Before PL 119-70, treatment depended on the definition: counted under Part 5 and Census, excluded under IRS 1040 (compensation is non-taxable). Congress cited that inconsistency (H. Rept. 118-652). | AC4: CDBG-DR funds come through supplemental appropriations that give HUD broad waiver authority; check whether any DR Federal Register notice alters the income definition. Hurricane Sandy grants are largely closed out. Statute (5302(a)(20)(C)) and 570.3 read this session; CPD-26-09's existence and date confirmed but its text could not be retrieved. | AD4: Partly verified
A5: 9 | B5: Community Development Block Grant Disaster Recovery (CDBG-DR) Assistance | C5: National Disaster Resilience Competition | D5: Community Planning and Development (CPD) | E5: Assistant Secretary for Community Planning and Development | F5: Flexible grants to help the most impacted and distressed areas recover long-term after Presidentially declared disasters. | G5: CDBG-DR assistance is largely governed by specific appropriations acts, most recently Public Law 117-328, and it is also subject to provisions of Title I of the Housing and Community Development Act of 1974 (42 U.S.C. 5301, et seq.) (made applicable by appropriations acts unless waived) and certain provisions of the Robert T. Stafford Disaster Relief and Emergency Assistance Act (42 U.S.C. 5121, et seq.). | I5: https://www.hud.gov/program_offices/comm_planning/cdbg-dr | J5: 14.272 | K5: Community Development Block Grant P. L. 113-2 | L5: The overall CDBG program objective is to develop viable urban communities, by providing decent housing and a suitable living environment, and by expanding economic opportunities, principally for persons of low and moderate income. The National Resilient Disaster Competition program funds appropriated by P.L. 113-2 are available for resilient recovery projects and necessary expenses related to disaster relief, long-term recovery, restoration of infrastructure and housing, and economic revitalization in the most impacted and distressed areas resulting from a major disaster declared pursuant to the due to Hurricane Sandy and other eligible events in calendar years 2011, 2012, and 2013. | M5: Project Grants | N5: Anyone/general public,Homeowner,Interstate,Local,Low Income,Moderate Income,Private nonprofit institution/organization,Profit organization,Public nonprofit institution/organization,Senior Citizen (60+),Small business,State | O5: Local (includes State-designated lndian Tribes, excludes institutions of higher education and hospitals,State,U.S. Territories and possessions | P5: 0 | Q5: 0 | R5: -606138.41 | S5: Household income test | T5: HCDA Title I (CDBG family) | U5: 42 U.S.C. 5302(a)(20)(C) (added by PL 119-70 §2); 24 CFR 570.3 'Income' | V5: Part 5 / Census long-form / IRS 1040 AGI (grantee picks per activity) | W5: Grantee menu | X5: Excluded | Y5: Not applicable | Z5: =IF(X5="","",IF(X5="Excluded","Consistent",IF(X5="Counted","Inconsistent",IF(X5="Varies (grantee/agency choice)","Partly inconsistent",IF(X5="Not applicable","Not applicable","Needs check"))))) | AA5: PL 119-70 §2 (Jan. 20, 2026) requires a State, unit of general local government, or Indian tribe to exclude VA service-connected disability compensation when determining whether a person is low/moderate income. HUD implemented it sub-regulatorily in Notice CPD-26-09 (posted Sept. 4, 2026). 24 CFR 570.3 has not been amended: its Census option still lists 'Veterans' (VA) payments' as income. | AB5: HCDA sets income limits (80% AMI) but left the income definition to HUD, which offered a three-definition menu (1995) to ease local administration. Before PL 119-70, treatment depended on the definition: counted under Part 5 and Census, excluded under IRS 1040 (compensation is non-taxable). Congress cited that inconsistency (H. Rept. 118-652). | AC5: National Disaster Resilience Competition (PL 113-2 CDBG-DR funds); same caveats as CDBG-DR. Statute (5302(a)(20)(C)) and 570.3 read this session; CPD-26-09's existence and date confirmed but its text could not be retrieved. | AD5: Partly verified
A6: 11 | B6: Community Development Block Grants (CDBG) (Entitlement) | C6: Community Development Block Grants/Entitlement Grants | D6: Community Planning and Development (CPD) | E6: Assistant Secretary for Community Planning and Development | F6: Funding to help metropolitan cities and urban counties meet their housing and community development needs. | G6: Title I, Housing and Community Development Act of 1974 (Public Law 93383, approved August 22, 1974) (42 U.S.C. 5301, et seq.). | H6: CDBG Program regulations are at 24 CFR part 570 and consolidated plan regulations are at 24 CFR part 91. | I6: https://www.hud.gov/program_offices/comm_planning/cdbg | J6: 14.218 | K6: Community Development Block Grant Program for Entitlement Communities. | L6: To develop viable urban communities by providing decent housing, a suitable living environment, and expanding economic opportunities, principally for persons of low and moderate income. | M6: Formula Grants | N6: Individual/Family,Low Income,Moderate Income | O6: Government - General | P6: 0 | Q6: 2.0931359e+09 | R6: 2.7687864e+09 | S6: Household income test | T6: HCDA Title I (CDBG family) | U6: 42 U.S.C. 5302(a)(20)(C) (added by PL 119-70 §2); 24 CFR 570.3 'Income' | V6: Part 5 / Census long-form / IRS 1040 AGI (grantee picks per activity) | W6: Grantee menu | X6: Excluded | Y6: Not applicable | Z6: =IF(X6="","",IF(X6="Excluded","Consistent",IF(X6="Counted","Inconsistent",IF(X6="Varies (grantee/agency choice)","Partly inconsistent",IF(X6="Not applicable","Not applicable","Needs check"))))) | AA6: PL 119-70 §2 (Jan. 20, 2026) requires a State, unit of general local government, or Indian tribe to exclude VA service-connected disability compensation when determining whether a person is low/moderate income. HUD implemented it sub-regulatorily in Notice CPD-26-09 (posted Sept. 4, 2026). 24 CFR 570.3 has not been amended: its Census option still lists 'Veterans' (VA) payments' as income. | AB6: HCDA sets income limits (80% AMI) but left the income definition to HUD, which offered a three-definition menu (1995) to ease local administration. Before PL 119-70, treatment depended on the definition: counted under Part 5 and Census, excluded under IRS 1040 (compensation is non-taxable). Congress cited that inconsistency (H. Rept. 118-652). | AC6: Area-benefit activities qualify using HUD's LMISD tabulations of ACS income, which include VA payments; PL 119-70 speaks to a person's income determination and doesn't obviously reach area data. CDBG sets no household rent formula, so rent is N/A. Statute (5302(a)(20)(C)) and 570.3 read this session; CPD-26-09's existence and date confirmed but its text could not be retrieved. | AD6: Partly verified
A7: 13 | B7: Community Development Block Grants for Insular Areas | C7: Community Development Block Grants/Special Purpose Grants/Insular Areas | D7: Community Planning and Development (CPD) | E7: Assistant Secretary for Community Planning and Development | F7: Funding to help certain U.S. territories meet their housing and community development needs. | G7: Title I, Housing and Community Development Act of 1974 (42 U.S.C. 5301, et seq.). | H7: CDBG Program regulations are at 24 CFR part 570 and consolidated plan regulations are at 24 CFR part 91. | I7: https://www.hud.gov/program_offices/comm_planning/cdbg | J7: 14.225 | K7: Insular CDBG | L7: To provide community development assistance to the Pacific Islands of American Samoa, Guam, the Northern Mariana Islands, and the Virgin Islands in the Caribbean, by providing decent housing, a suitable living environment, and expanding economic opportunities, principally for persons of low- and moderate-income. Each activity funded must meet one of the program's National Objectives by: Benefiting low- and moderate-income families; aiding in the prevention or elimination of slums or blight; or meeting other community development needs having a particular urgency because existing conditions pose a serious and immediate threat to the health or welfare of the community where other financial resources are not available. | M7: Formula Grants | N7: Low Income,Moderate Income,U.S. Territories | O7: U.S. Territories and possessions (includes institutions of higher education and hospitals) | P7: 0 | Q7: 6019875 | R7: 7846826.7 | S7: Household income test | T7: HCDA Title I (CDBG family) | U7: 42 U.S.C. 5302(a)(20)(C) (added by PL 119-70 §2); 24 CFR 570.3 'Income' | V7: Part 5 / Census long-form / IRS 1040 AGI (grantee picks per activity) | W7: Grantee menu | X7: Excluded | Y7: Not applicable | Z7: =IF(X7="","",IF(X7="Excluded","Consistent",IF(X7="Counted","Inconsistent",IF(X7="Varies (grantee/agency choice)","Partly inconsistent",IF(X7="Not applicable","Not applicable","Needs check"))))) | AA7: PL 119-70 §2 (Jan. 20, 2026) requires a State, unit of general local government, or Indian tribe to exclude VA service-connected disability compensation when determining whether a person is low/moderate income. HUD implemented it sub-regulatorily in Notice CPD-26-09 (posted Sept. 4, 2026). 24 CFR 570.3 has not been amended: its Census option still lists 'Veterans' (VA) payments' as income. | AB7: HCDA sets income limits (80% AMI) but left the income definition to HUD, which offered a three-definition menu (1995) to ease local administration. Before PL 119-70, treatment depended on the definition: counted under Part 5 and Census, excluded under IRS 1040 (compensation is non-taxable). Congress cited that inconsistency (H. Rept. 118-652). | AC7: Insular Areas CDBG follows part 570 rules. Statute (5302(a)(20)(C)) and 570.3 read this session; CPD-26-09's existence and date confirmed but its text could not be retrieved. | AD7: Partly verified
A8: 14 | B8: Community Development Block Grants (Non-Entitlement) for States and Small Cities | C8: Community Development Block Grants/State's program and Non-Entitlement Grants in Hawaii | D8: Community Planning and Development (CPD) | E8: Assistant Secretary for Community Planning and Development | F8: Funding to help States and units of local government in non-entitlement areas meet their housing and community development needs. | G8: Title I, Housing and Community Development Act of 1974 (42 U.S.C. 5301, et seq.). | H8: CDBG program regulations are at 24 CFR part 570 and consolidated plan regulations are at 24 CFR part 91. | I8: https://www.hud.gov/program_offices/comm_planning/cdbg | J8: 14.228 | K8: State CDBG | L8: The primary objective of this program is the development of viable urban communities by providing decent housing, a suitable living environment, and expanding economic opportunities, principally for persons of low- and moderate-income. Each activity funded must meet one of the program's National Objectives by: Benefiting low- and moderate-income families; aiding in the prevention or elimination of slums or blight; or meeting other community development needs having a particular urgency because existing conditions pose a serious and immediate threat to the health or welfare of the community where other financial resources are not available. | M8: Formula Grants | N8: Local,Low Income,Moderate Income | O8: State (includes District of Columbia, public institutions of higher education and hospitals) | P8: 0 | Q8: 5.1150088e+09 | R8: 7.0780724e+09 | S8: Household income test | T8: HCDA Title I (CDBG family) | U8: 42 U.S.C. 5302(a)(20)(C) (added by PL 119-70 §2); 24 CFR 570.3 'Income' | V8: Part 5 / Census long-form / IRS 1040 AGI (grantee picks per activity) | W8: Grantee menu | X8: Excluded | Y8: Not applicable | Z8: =IF(X8="","",IF(X8="Excluded","Consistent",IF(X8="Counted","Inconsistent",IF(X8="Varies (grantee/agency choice)","Partly inconsistent",IF(X8="Not applicable","Not applicable","Needs check"))))) | AA8: PL 119-70 §2 (Jan. 20, 2026) requires a State, unit of general local government, or Indian tribe to exclude VA service-connected disability compensation when determining whether a person is low/moderate income. HUD implemented it sub-regulatorily in Notice CPD-26-09 (posted Sept. 4, 2026). 24 CFR 570.3 has not been amended: its Census option still lists 'Veterans' (VA) payments' as income. | AB8: HCDA sets income limits (80% AMI) but left the income definition to HUD, which offered a three-definition menu (1995) to ease local administration. Before PL 119-70, treatment depended on the definition: counted under Part 5 and Census, excluded under IRS 1040 (compensation is non-taxable). Congress cited that inconsistency (H. Rept. 118-652). | AC8: States' own income-definition rules (24 CFR 570.481–.483) were not checked; PL 119-70 applies to States by its terms. Statute (5302(a)(20)(C)) and 570.3 read this session; CPD-26-09's existence and date confirmed but its text could not be retrieved. | AD8: Partly verified
A9: 15 | B9: Community Development Block Grants (Section 108 Loan Guarantee) | C9: Community Development Block Grants Section 108 Loan Guarantees | D9: Community Planning and Development (CPD) | E9: Assistant Secretary for Community Planning and Development | F9: Loan guarantee assistance for community and economic development. | G9: Section 108 of the Housing and Community Development Act of 1974 (42 U.S.C. 5308). | H9: Regulations are at 24 CFR part 570. | I9: https://www.hud.gov/program_offices/comm_planning/section108 | J9: 14.248 | K9: (Section 108) | L9: To provide communities with a source of financing for economic development, housing rehabilitation, public facilities, and large scale physical development projects. | M9: Guaranteed / Insured Loans | N9: Individual/Family,Low Income,Moderate Income | O9: Government - General,Other public institution/organization,State,U.S. Territories and possessions | P9: 0 | Q9: 0 | R9: 0 | S9: Household income test | T9: HCDA Title I (CDBG family) | U9: 42 U.S.C. 5302(a)(20)(C) (added by PL 119-70 §2); 24 CFR 570.3 'Income' | V9: Part 5 / Census long-form / IRS 1040 AGI (grantee picks per activity) | W9: Grantee menu | X9: Excluded | Y9: Not applicable | Z9: =IF(X9="","",IF(X9="Excluded","Consistent",IF(X9="Counted","Inconsistent",IF(X9="Varies (grantee/agency choice)","Partly inconsistent",IF(X9="Not applicable","Not applicable","Needs check"))))) | AA9: PL 119-70 §2 (Jan. 20, 2026) requires a State, unit of general local government, or Indian tribe to exclude VA service-connected disability compensation when determining whether a person is low/moderate income. HUD implemented it sub-regulatorily in Notice CPD-26-09 (posted Sept. 4, 2026). 24 CFR 570.3 has not been amended: its Census option still lists 'Veterans' (VA) payments' as income. | AB9: HCDA sets income limits (80% AMI) but left the income definition to HUD, which offered a three-definition menu (1995) to ease local administration. Before PL 119-70, treatment depended on the definition: counted under Part 5 and Census, excluded under IRS 1040 (compensation is non-taxable). Congress cited that inconsistency (H. Rept. 118-652). | AC9: Section 108 guaranteed activities must meet CDBG national objectives, so the same low/mod determination applies. Statute (5302(a)(20)(C)) and 570.3 read this session; CPD-26-09's existence and date confirmed but its text could not be retrieved. | AD9: Partly verified
A10: 17 | B10: Continuum of Care Program | C10: Continuum of Care Program | D10: Community Planning and Development (CPD) | E10: Assistant Secretary for Community Planning and Development | F10: Promotes community-wide commitment to the goal of ending homelessness; provides funding for efforts to quickly re-house homeless individuals and families while minimizing trauma and dislocation; promotes access to and effective utilization of mainstream programs; and optimizes self-sufficiency among individuals and families experiencing homelessness. | G10: Subtitle C of Title IV of the McKinney-Vento Homeless Assistance Act (42 U.S.C. 11381-11389). | H10: Regulations are at 24 CFR part 578. | I10: https://www.hud.gov/program_offices/comm_planning/coc | J10: 14.267 | K10: See Notice of Funding Opportunity [NOFO] for additional information. | L10: The program is designed to promote community-wide commitment to the goal of ending homelessness; provide funding for efforts by nonprofit providers, States, and local governments to quickly house homeless individuals and families while minimizing the trauma and dislocation caused to homeless individuals, families, and communities by homelessness; promote access to and effective utilization of mainstream programs by homeless individuals and families; and optimize self-sufficiency among individuals and families experiencing homelessness. Continuum of Care Program funds may be used to pay for the eligible costs used to establish and operate projects under five program components: (i) permanent housing, which includes permanent supportive housing for persons with disabilities, and rapid rehousing; (ii) transitional housing; (iii) supportive services only; (iv) Homeless Management Information Systems (HMIS), and (v) in some cases, homelessness prevention. | M10: Project Grants | N10: Individual/Family | O10: Government - General,Local (includes State-designated lndian Tribes, excludes institutions of higher education and hospitals,Other private institutions/organizations,Quasi-public nonprofit institution/organization,Specialized group (e.g. health professionals, students, veterans),State | P10: 0 | Q10: 2965446336 | R10: 2.5883551e+09 | S10: Varies by component | T10: McKinney-Vento / AIDS Housing Opportunity Act | U10: McKinney-Vento Act Title IV (HEARTH); 24 CFR 578.77 | V10: Part 5 (5.609 and 5.611(a)) for occupancy charges/rent | W10: Mandatory | X10: Not applicable | Y10: Counted | Z10: =IF(X10="","",IF(X10="Excluded","Consistent",IF(X10="Counted","Inconsistent",IF(X10="Varies (grantee/agency choice)","Partly inconsistent",IF(X10="Not applicable","Not applicable","Needs check"))))) | AA10: Eligibility is based on homelessness (and disability for PSH), not income, so there is no income eligibility test. When occupancy charges or rent are charged, 578.77 requires income to be calculated under 24 CFR 5.609/5.611(a), so VA compensation counts. | AB10: CPD homeless programs borrow the Part 5 definition because they set ongoing rent/occupancy charges like 1937 Act programs. | AC10: No eligibility inconsistency with PL 119-70 (which is eligibility-only), but VA compensation raises the participant's rent contribution. | AD10: Partly verified
A11: 18 | B11: Emergency Solutions Grants (ESG) Program | C11: Emergency Solutions Grant Program | D11: Community Planning and Development (CPD) | E11: Assistant Secretary for Community Planning and Development | F11: Formula grants to provide emergency assistance to people who are homeless or at risk of homelessness and help them quickly regain stability in permanent housing. | G11: Subtitle B of Title IV of the McKinney-Vento Homeless Assistance Act (42 U.S.C. 11371-11378). | H11: Regulations are at 24 CFR part 576. | I11: https://www.hud.gov/program_offices/comm_planning/esg | J11: 14.231 | K11: Emergency Solutions Grants Program | L11: The ESG program provides funding to: (1) engage homeless individuals and families living on the street; (2) improve the number and quality of emergency shelters for homeless individuals and families; (3) help operate these shelters; (4) provide essential services to shelter residents, (5) rapidly re-house homeless individuals and families, and (6) prevent families and individuals from becoming homeless. | M11: Formula Grants | N11: Anyone/general public,Individual/Family | O11: Government - General | P11: 0 | Q11: 2.9616491e+08 | R11: 3.7341986e+08 | S11: Varies by component | T11: McKinney-Vento / AIDS Housing Opportunity Act | U11: McKinney-Vento Act Title IV (HEARTH); 24 CFR 576.103, 576.401(b)–(c) | V11: Part 5 annual income (5.609) | W11: Mandatory | X11: Counted | Y11: Counted | Z11: =IF(X11="","",IF(X11="Excluded","Consistent",IF(X11="Counted","Inconsistent",IF(X11="Varies (grantee/agency choice)","Partly inconsistent",IF(X11="Not applicable","Not applicable","Needs check"))))) | AA11: 576.401(c) requires recipients to use 5.609 when calculating annual income. Homelessness prevention requires income below 30% AMI at intake (576.103); prevention and rapid re-housing participants must stay at or below 30% AMI at re-evaluation (576.401(b)). VA compensation counts toward those tests. | AB11: Same Part 5 borrowing as CoC; ESG's 30% AMI test targets scarce prevention funds. | AC11: Emergency shelter and street outreach have no income test. Participant rent share is set by the recipient's written standards; where it is income-based, 5.609 applies. | AD11: Verified — primary source
